{"header":{"callVolume":14656.0,"putVolume":1198.0,"cpRatio":12.23,"callOi":837878.0,"putOi":169473.0,"cputOiRatio":4.94,"underlyingPrice":0},"contracts":[{"callOption":"2026-06-05_10.00_Call","callPrice":0.01,"callDelta":0.0,"callVolume":0,"callIv":548.0,"callOi":365,"putOption":"2026-06-05_10.00_Put","putPrice":5.28,"putDelta":-0.99,"putVolume":1,"putIv":558.77,"putOi":1},{"callOption":"2026-06-05_1.00_Call","callPrice":4.05,"callDelta":1.0,"callVolume":1,"callIv":0.0,"callOi":76,"putOption":"2026-06-05_1.00_Put","putPrice":0.01,"putDelta":0.0,"putVolume":1,"putIv":1319.17,"putOi":0},{"callOption":"2026-06-05_0.50_Call","callPrice":4.37,"callDelta":1.0,"callVolume":0,"callIv":0.0,"callOi":78,"putOption":"2026-06-05_0.50_Put","putPrice":0.01,"putDelta":0.0,"putVolume":0,"putIv":0.0,"putOi":0},{"callOption":"2026-06-05_9.50_Call","callPrice":0.01,"callDelta":0.0,"callVolume":0,"callIv":513.89,"callOi":133,"putOption":"2026-06-05_9.50_Put","putPrice":4.35,"putDelta":-1.0,"putVolume":0,"putIv":0.0,"putOi":1},{"callOption":"2026-06-05_9.00_Call","callPrice":0.12,"callDelta":0.0,"callVolume":0,"callIv":477.46,"callOi":29,"putOption":"2026-06-05_9.00_Put","putPrice":3.6,"putDelta":-1.0,"putVolume":0,"putIv":763.84,"putOi":4},{"callOption":"2026-06-05_8.50_Call","callPrice":0.02,"callDelta":0.0,"callVolume":0,"callIv":438.39,"callOi":113,"putOption":"2026-06-05_8.50_Put","putPrice":3.6,"putDelta":-0.89,"putVolume":1,"putIv":710.98,"putOi":4},{"callOption":"2026-06-05_8.00_Call","callPrice":0.01,"callDelta":0.03,"callVolume":4,"callIv":465.24,"callOi":2223,"putOption":"2026-06-05_8.00_Put","putPrice":2.9,"putDelta":-0.97,"putVolume":0,"putIv":653.45,"putOi":2},{"callOption":"2026-06-05_7.50_Call","callPrice":0.01,"callDelta":0.02,"callVolume":3,"callIv":350.44,"callOi":1926,"putOption":"2026-06-05_7.50_Put","putPrice":2.62,"putDelta":-0.98,"putVolume":0,"putIv":590.3,"putOi":22},{"callOption":"2026-06-05_7.00_Call","callPrice":0.01,"callDelta":0.0,"callVolume":0,"callIv":300.28,"callOi":13241,"putOption":"2026-06-05_7.00_Put","putPrice":2.2,"putDelta":-0.85,"putVolume":1,"putIv":546.08,"putOi":63},{"callOption":"2026-06-05_6.50_Call","callPrice":0.01,"callDelta":0.02,"callVolume":4,"callIv":244.69,"callOi":11313,"putOption":"2026-06-05_6.50_Put","putPrice":1.61,"putDelta":-0.98,"putVolume":0,"putIv":0.0,"putOi":367},{"callOption":"2026-06-05_6.00_Call","callPrice":0.02,"callDelta":0.06,"callVolume":1381,"callIv":223.02,"callOi":21399,"putOption":"2026-06-05_6.00_Put","putPrice":1.09,"putDelta":-0.94,"putVolume":0,"putIv":0.0,"putOi":350},{"callOption":"2026-06-05_5.50_Call","callPrice":0.04,"callDelta":0.15,"callVolume":2122,"callIv":176.59,"callOi":24305,"putOption":"2026-06-05_5.50_Put","putPrice":0.55,"putDelta":-0.75,"putVolume":204,"putIv":258.79,"putOi":5663},{"callOption":"2026-06-05_5.00_Call","callPrice":0.14,"callDelta":0.5,"callVolume":3375,"callIv":148.24,"callOi":23270,"putOption":"2026-06-05_5.00_Put","putPrice":0.17,"putDelta":-0.5,"putVolume":282,"putIv":148.97,"putOi":12711},{"callOption":"2026-06-05_4.50_Call","callPrice":0.46,"callDelta":0.89,"callVolume":287,"callIv":165.29,"callOi":3201,"putOption":"2026-06-05_4.50_Put","putPrice":0.02,"putDelta":-0.11,"putVolume":270,"putIv":166.78,"putOi":6221},{"callOption":"2026-06-05_4.00_Call","callPrice":0.97,"callDelta":0.85,"callVolume":10,"callIv":450.04,"callOi":344,"putOption":"2026-06-05_4.00_Put","putPrice":0.01,"putDelta":-0.02,"putVolume":4,"putIv":215.79,"putOi":2458},{"callOption":"2026-06-05_3.50_Call","callPrice":1.96,"callDelta":1.0,"callVolume":0,"callIv":0.0,"callOi":159,"putOption":"2026-06-05_3.50_Put","putPrice":0.01,"putDelta":0.0,"putVolume":0,"putIv":325.72,"putOi":645},{"callOption":"2026-06-05_3.00_Call","callPrice":1.96,"callDelta":1.0,"callVolume":0,"callIv":0.0,"callOi":10,"putOption":"2026-06-05_3.00_Put","putPrice":0.01,"putDelta":0.0,"putVolume":0,"putIv":449.11,"putOi":4},{"callOption":"2026-06-05_2.50_Call","callPrice":2.76,"callDelta":0.94,"callVolume":1,"callIv":1017.24,"callOi":20,"putOption":"2026-06-05_2.50_Put","putPrice":0.02,"putDelta":-0.06,"putVolume":0,"putIv":592.91,"putOi":4},{"callOption":"2026-06-05_2.00_Call","callPrice":2.95,"callDelta":1.0,"callVolume":0,"callIv":0.0,"callOi":135,"putOption":"2026-06-05_2.00_Put","putPrice":0.01,"putDelta":-0.01,"putVolume":0,"putIv":767.99,"putOi":0},{"callOption":"2026-06-05_1.50_Call","callPrice":3.41,"callDelta":1.0,"callVolume":0,"callIv":0.0,"callOi":133,"putOption":"2026-06-05_1.50_Put","putPrice":0.01,"putDelta":-0.01,"putVolume":0,"putIv":994.57,"putOi":0},{"callOption":"2026-06-12_0.50_Call","callPrice":4.42,"callDelta":1.0,"callVolume":0,"callIv":0.0,"callOi":182,"putOption":"2026-06-12_0.50_Put","putPrice":0.01,"putDelta":0.0,"putVolume":0,"putIv":671.34,"putOi":0},{"callOption":"2026-06-12_10.00_Call","callPrice":0.01,"callDelta":0.0,"callVolume":0,"callIv":274.51,"callOi":197,"putOption":"2026-06-12_10.00_Put","putPrice":5.3,"putDelta":-0.9,"putVolume":0,"putIv":307.12,"putOi":0},{"callOption":"2026-06-12_1.00_Call","callPrice":3.85,"callDelta":1.0,"callVolume":0,"callIv":0.0,"callOi":34,"putOption":"2026-06-12_1.00_Put","putPrice":0.01,"putDelta":0.0,"putVolume":0,"putIv":466.58,"putOi":0},{"callOption":"2026-06-12_9.50_Call","callPrice":0.01,"callDelta":0.01,"callVolume":0,"callIv":259.31,"callOi":12,"putOption":"2026-06-12_9.50_Put","putPrice":4.85,"putDelta":-0.72,"putVolume":0,"putIv":468.38,"putOi":0},{"callOption":"2026-06-12_9.00_Call","callPrice":0.01,"callDelta":0.01,"callVolume":0,"callIv":196.32,"callOi":184,"putOption":"2026-06-12_9.00_Put","putPrice":3.82,"putDelta":-0.99,"putVolume":0,"putIv":273.23,"putOi":4},{"callOption":"2026-06-12_8.50_Call","callPrice":0.02,"callDelta":0.01,"callVolume":8,"callIv":154.82,"callOi":1610,"putOption":"2026-06-12_8.50_Put","putPrice":3.6,"putDelta":-0.89,"putVolume":0,"putIv":254.28,"putOi":0},{"callOption":"2026-06-12_8.00_Call","callPrice":0.01,"callDelta":0.03,"callVolume":0,"callIv":172.48,"callOi":684,"putOption":"2026-06-12_8.00_Put","putPrice":2.88,"putDelta":-0.97,"putVolume":0,"putIv":233.67,"putOi":2},{"callOption":"2026-06-12_7.50_Call","callPrice":0.01,"callDelta":0.05,"callVolume":55,"callIv":153.73,"callOi":1377,"putOption":"2026-06-12_7.50_Put","putPrice":2.43,"putDelta":-0.95,"putVolume":0,"putIv":211.07,"putOi":2},{"callOption":"2026-06-12_7.00_Call","callPrice":0.03,"callDelta":0.05,"callVolume":125,"callIv":133.08,"callOi":5228,"putOption":"2026-06-12_7.00_Put","putPrice":2.1,"putDelta":-0.95,"putVolume":0,"putIv":256.49,"putOi":62},{"callOption":"2026-06-12_6.50_Call","callPrice":0.04,"callDelta":0.09,"callVolume":31,"callIv":124.47,"callOi":5052,"putOption":"2026-06-12_6.50_Put","putPrice":1.65,"putDelta":-0.82,"putVolume":1,"putIv":171.42,"putOi":245},{"callOption":"2026-06-12_6.00_Call","callPrice":0.06,"callDelta":0.16,"callVolume":499,"callIv":114.98,"callOi":12550,"putOption":"2026-06-12_6.00_Put","putPrice":1.18,"putDelta":-0.75,"putVolume":2,"putIv":157.74,"putOi":132},{"callOption":"2026-06-12_5.50_Call","callPrice":0.12,"callDelta":0.28,"callVolume":198,"callIv":103.15,"callOi":12470,"putOption":"2026-06-12_5.50_Put","putPrice":0.63,"putDelta":-0.7,"putVolume":16,"putIv":108.73,"putOi":778},{"callOption":"2026-06-12_5.00_Call","callPrice":0.28,"callDelta":0.52,"callVolume":602,"callIv":96.07,"callOi":4147,"putOption":"2026-06-12_5.00_Put","putPrice":0.29,"putDelta":-0.48,"putVolume":20,"putIv":95.74,"putOi":3712},{"callOption":"2026-06-12_4.50_Call","callPrice":0.56,"callDelta":0.79,"callVolume":283,"callIv":92.83,"callOi":1911,"putOption":"2026-06-12_4.50_Put","putPrice":0.12,"putDelta":-0.21,"putVolume":1,"putIv":94.62,"putOi":2316},{"callOption":"2026-06-12_4.00_Call","callPrice":0.92,"callDelta":0.95,"callVolume":1,"callIv":95.87,"callOi":1225,"putOption":"2026-06-12_4.00_Put","putPrice":0.03,"putDelta":-0.05,"putVolume":0,"putIv":105.45,"putOi":589},{"callOption":"2026-06-12_3.50_Call","callPrice":2.0,"callDelta":0.95,"callVolume":0,"callIv":510.02,"callOi":290,"putOption":"2026-06-12_3.50_Put","putPrice":0.01,"putDelta":-0.07,"putVolume":1,"putIv":177.43,"putOi":439},{"callOption":"2026-06-12_3.00_Call","callPrice":1.75,"callDelta":0.99,"callVolume":0,"callIv":0.0,"callOi":96,"putOption":"2026-06-12_3.00_Put","putPrice":0.01,"putDelta":-0.02,"putVolume":0,"putIv":176.71,"putOi":0},{"callOption":"2026-06-12_2.50_Call","callPrice":2.46,"callDelta":1.0,"callVolume":0,"callIv":0.0,"callOi":2,"putOption":"2026-06-12_2.50_Put","putPrice":0.01,"putDelta":-0.01,"putVolume":0,"putIv":209.81,"putOi":0},{"callOption":"2026-06-12_2.00_Call","callPrice":2.93,"callDelta":1.0,"callVolume":0,"callIv":0.0,"callOi":1,"putOption":"2026-06-12_2.00_Put","putPrice":0.01,"putDelta":0.0,"putVolume":0,"putIv":271.71,"putOi":5},{"callOption":"2026-06-12_1.50_Call","callPrice":3.25,"callDelta":1.0,"callVolume":0,"callIv":0.0,"callOi":24,"putOption":"2026-06-12_1.50_Put","putPrice":0.01,"putDelta":-0.01,"putVolume":0,"putIv":351.82,"putOi":0},{"callOption":"2026-06-18_8.50_Call","callPrice":0.02,"callDelta":0.07,"callVolume":0,"callIv":162.64,"callOi":324,"putOption":"2026-06-18_8.50_Put","putPrice":3.75,"putDelta":-0.93,"putVolume":0,"putIv":193.95,"putOi":2},{"callOption":"2026-06-18_7.50_Call","callPrice":0.03,"callDelta":0.13,"callVolume":0,"callIv":125.43,"callOi":2727,"putOption":"2026-06-18_7.50_Put","putPrice":2.72,"putDelta":-0.87,"putVolume":0,"putIv":183.28,"putOi":72},{"callOption":"2026-06-18_6.50_Call","callPrice":0.07,"callDelta":0.13,"callVolume":3,"callIv":107.85,"callOi":4244,"putOption":"2026-06-18_6.50_Put","putPrice":1.63,"putDelta":-0.87,"putVolume":0,"putIv":115.95,"putOi":86},{"callOption":"2026-06-18_5.50_Call","callPrice":0.2,"callDelta":0.34,"callVolume":184,"callIv":96.59,"callOi":6554,"putOption":"2026-06-18_5.50_Put","putPrice":0.76,"putDelta":-0.56,"putVolume":10,"putIv":166.51,"putOi":1120},{"callOption":"2026-06-18_4.50_Call","callPrice":0.63,"callDelta":0.75,"callVolume":79,"callIv":91.36,"callOi":2885,"putOption":"2026-06-18_4.50_Put","putPrice":0.16,"putDelta":-0.26,"putVolume":31,"putIv":93.39,"putOi":3043},{"callOption":"2026-06-18_3.50_Call","callPrice":1.92,"callDelta":0.9,"callVolume":0,"callIv":386.97,"callOi":225,"putOption":"2026-06-18_3.50_Put","putPrice":0.01,"putDelta":-0.1,"putVolume":0,"putIv":157.69,"putOi":741},{"callOption":"2026-06-18_2.50_Call","callPrice":2.79,"callDelta":0.99,"callVolume":0,"callIv":0.0,"callOi":1,"putOption":"2026-06-18_2.50_Put","putPrice":0.27,"putDelta":-0.1,"putVolume":0,"putIv":397.69,"putOi":0},{"callOption":"2026-06-18_1.50_Call","callPrice":4.05,"callDelta":1.0,"callVolume":0,"callIv":0.0,"callOi":44,"putOption":"2026-06-18_1.50_Put","putPrice":0.01,"putDelta":-0.01,"putVolume":0,"putIv":266.07,"putOi":0},{"callOption":"2026-06-18_0.50_Call","callPrice":5.14,"callDelta":1.0,"callVolume":0,"callIv":0.0,"callOi":63,"putOption":"2026-06-18_0.50_Put","putPrice":0.01,"putDelta":0.0,"putVolume":0,"putIv":507.61,"putOi":0},{"callOption":"2026-06-18_10.00_Call","callPrice":0.02,"callDelta":0.03,"callVolume":28,"callIv":169.2,"callOi":4749,"putOption":"2026-06-18_10.00_Put","putPrice":5.1,"putDelta":-0.9,"putVolume":0,"putIv":234.33,"putOi":0},{"callOption":"2026-06-18_9.00_Call","callPrice":0.03,"callDelta":0.05,"callVolume":0,"callIv":155.23,"callOi":4068,"putOption":"2026-06-18_9.00_Put","putPrice":4.6,"putDelta":-0.86,"putVolume":0,"putIv":233.51,"putOi":0},{"callOption":"2026-06-18_8.00_Call","callPrice":0.03,"callDelta":0.04,"callVolume":1,"callIv":130.25,"callOi":3443,"putOption":"2026-06-18_8.00_Put","putPrice":3.1,"putDelta":-0.96,"putVolume":0,"putIv":201.58,"putOi":8},{"callOption":"2026-06-18_7.00_Call","callPrice":0.04,"callDelta":0.09,"callVolume":70,"callIv":119.35,"callOi":13842,"putOption":"2026-06-18_7.00_Put","putPrice":2.1,"putDelta":-0.91,"putVolume":0,"putIv":157.0,"putOi":312},{"callOption":"2026-06-18_6.00_Call","callPrice":0.11,"callDelta":0.21,"callVolume":331,"callIv":102.27,"callOi":27550,"putOption":"2026-06-18_6.00_Put","putPrice":1.2,"putDelta":-0.71,"putVolume":2,"putIv":137.05,"putOi":620},{"callOption":"2026-06-18_5.00_Call","callPrice":0.36,"callDelta":0.53,"callVolume":407,"callIv":94.16,"callOi":11247,"putOption":"2026-06-18_5.00_Put","putPrice":0.36,"putDelta":-0.47,"putVolume":10,"putIv":95.91,"putOi":6723},{"callOption":"2026-06-18_4.00_Call","callPrice":1.02,"callDelta":0.81,"callVolume":3,"callIv":0.0,"callOi":1002,"putOption":"2026-06-18_4.00_Put","putPrice":0.05,"putDelta":-0.09,"putVolume":11,"putIv":90.25,"putOi":2977},{"callOption":"2026-06-18_3.00_Call","callPrice":2.0,"callDelta":0.96,"callVolume":5,"callIv":0.0,"callOi":848,"putOption":"2026-06-18_3.00_Put","putPrice":0.01,"putDelta":-0.04,"putVolume":0,"putIv":143.36,"putOi":1138},{"callOption":"2026-06-18_2.00_Call","callPrice":3.5,"callDelta":1.0,"callVolume":0,"callIv":0.0,"callOi":15,"putOption":"2026-06-18_2.00_Put","putPrice":0.03,"putDelta":0.0,"putVolume":0,"putIv":205.51,"putOi":5},{"callOption":"2026-06-18_1.00_Call","callPrice":4.55,"callDelta":1.0,"callVolume":0,"callIv":0.0,"callOi":12,"putOption":"2026-06-18_1.00_Put","putPrice":0.01,"putDelta":0.0,"putVolume":0,"putIv":352.83,"putOi":0},{"callOption":"2026-06-26_10.00_Call","callPrice":0.04,"callDelta":0.06,"callVolume":0,"callIv":146.04,"callOi":389,"putOption":"2026-06-26_10.00_Put","putPrice":5.13,"putDelta":-0.88,"putVolume":0,"putIv":200.04,"putOi":0},{"callOption":"2026-06-26_1.00_Call","callPrice":4.45,"callDelta":1.0,"callVolume":0,"callIv":0.0,"callOi":141,"putOption":"2026-06-26_1.00_Put","putPrice":0.38,"putDelta":-0.04,"putVolume":0,"putIv":789.51,"putOi":0},{"callOption":"2026-06-26_9.50_Call","callPrice":0.08,"callDelta":0.08,"callVolume":0,"callIv":152.93,"callOi":1,"putOption":"2026-06-26_9.50_Put","putPrice":5.4,"putDelta":-0.82,"putVolume":0,"putIv":224.35,"putOi":0},{"callOption":"2026-06-26_9.00_Call","callPrice":0.05,"callDelta":0.1,"callVolume":0,"callIv":146.28,"callOi":210,"putOption":"2026-06-26_9.00_Put","putPrice":4.15,"putDelta":-0.85,"putVolume":0,"putIv":187.9,"putOi":0},{"callOption":"2026-06-26_8.50_Call","callPrice":0.03,"callDelta":0.06,"callVolume":2,"callIv":126.26,"callOi":624,"putOption":"2026-06-26_8.50_Put","putPrice":3.0,"putDelta":-0.94,"putVolume":0,"putIv":263.48,"putOi":65},{"callOption":"2026-06-26_8.00_Call","callPrice":0.06,"callDelta":0.16,"callVolume":0,"callIv":129.29,"callOi":557,"putOption":"2026-06-26_8.00_Put","putPrice":3.2,"putDelta":-0.84,"putVolume":0,"putIv":185.28,"putOi":75},{"callOption":"2026-06-26_7.50_Call","callPrice":0.07,"callDelta":0.21,"callVolume":0,"callIv":120.84,"callOi":1421,"putOption":"2026-06-26_7.50_Put","putPrice":2.44,"putDelta":-0.79,"putVolume":0,"putIv":147.44,"putOi":138},{"callOption":"2026-06-26_7.00_Call","callPrice":0.1,"callDelta":0.18,"callVolume":1,"callIv":127.31,"callOi":3095,"putOption":"2026-06-26_7.00_Put","putPrice":2.2,"putDelta":-0.82,"putVolume":0,"putIv":184.68,"putOi":21},{"callOption":"2026-06-26_6.50_Call","callPrice":0.12,"callDelta":0.18,"callVolume":100,"callIv":104.74,"callOi":1515,"putOption":"2026-06-26_6.50_Put","putPrice":1.66,"putDelta":-0.82,"putVolume":0,"putIv":156.94,"putOi":80},{"callOption":"2026-06-26_6.00_Call","callPrice":0.18,"callDelta":0.27,"callVolume":128,"callIv":101.21,"callOi":6662,"putOption":"2026-06-26_6.00_Put","putPrice":1.31,"putDelta":-0.73,"putVolume":0,"putIv":279.01,"putOi":271},{"callOption":"2026-06-26_5.50_Call","callPrice":0.3,"callDelta":0.39,"callVolume":77,"callIv":98.57,"callOi":4952,"putOption":"2026-06-26_5.50_Put","putPrice":0.78,"putDelta":-0.61,"putVolume":0,"putIv":97.7,"putOi":208},{"callOption":"2026-06-26_5.00_Call","callPrice":0.44,"callDelta":0.54,"callVolume":243,"callIv":93.28,"callOi":7541,"putOption":"2026-06-26_5.00_Put","putPrice":0.49,"putDelta":-0.46,"putVolume":90,"putIv":89.25,"putOi":1520},{"callOption":"2026-06-26_4.50_Call","callPrice":0.68,"callDelta":0.76,"callVolume":1,"callIv":68.35,"callOi":524,"putOption":"2026-06-26_4.50_Put","putPrice":0.22,"putDelta":-0.28,"putVolume":103,"putIv":89.62,"putOi":1452},{"callOption":"2026-06-26_4.00_Call","callPrice":1.05,"callDelta":0.78,"callVolume":0,"callIv":0.0,"callOi":197,"putOption":"2026-06-26_4.00_Put","putPrice":0.09,"putDelta":-0.22,"putVolume":0,"putIv":107.0,"putOi":584},{"callOption":"2026-06-26_3.50_Call","callPrice":1.48,"callDelta":0.87,"callVolume":0,"callIv":138.25,"callOi":158,"putOption":"2026-06-26_3.50_Put","putPrice":0.03,"putDelta":-0.13,"putVolume":0,"putIv":232.72,"putOi":406},{"callOption":"2026-06-26_3.00_Call","callPrice":2.2,"callDelta":0.93,"callVolume":0,"callIv":347.87,"callOi":388,"putOption":"2026-06-26_3.00_Put","putPrice":0.03,"putDelta":-0.07,"putVolume":0,"putIv":291.96,"putOi":272},{"callOption":"2026-06-26_2.50_Call","callPrice":2.22,"callDelta":0.97,"callVolume":0,"callIv":0.0,"callOi":1,"putOption":"2026-06-26_2.50_Put","putPrice":0.38,"putDelta":-0.11,"putVolume":0,"putIv":364.26,"putOi":0},{"callOption":"2026-06-26_2.00_Call","callPrice":2.75,"callDelta":0.99,"callVolume":0,"callIv":0.0,"callOi":0,"putOption":"2026-06-26_2.00_Put","putPrice":0.01,"putDelta":-0.01,"putVolume":0,"putIv":211.28,"putOi":278},{"callOption":"2026-06-26_1.50_Call","callPrice":3.44,"callDelta":1.0,"callVolume":0,"callIv":0.0,"callOi":20,"putOption":"2026-06-26_1.50_Put","putPrice":0.38,"putDelta":-0.06,"putVolume":0,"putIv":582.2,"putOi":0},{"callOption":"2026-07-02_10.00_Call","callPrice":0.38,"callDelta":0.25,"callVolume":0,"callIv":246.74,"callOi":0,"putOption":"2026-07-02_10.00_Put","putPrice":5.15,"putDelta":-0.86,"putVolume":0,"putIv":187.22,"putOi":0},{"callOption":"2026-07-02_8.50_Call","callPrice":0.05,"callDelta":0.17,"callVolume":0,"callIv":120.15,"callOi":423,"putOption":"2026-07-02_8.50_Put","putPrice":3.0,"putDelta":-0.83,"putVolume":0,"putIv":156.58,"putOi":4},{"callOption":"2026-07-02_8.00_Call","callPrice":0.08,"callDelta":0.13,"callVolume":18,"callIv":131.58,"callOi":702,"putOption":"2026-07-02_8.00_Put","putPrice":2.93,"putDelta":0.0,"putVolume":0,"putIv":0.0,"putOi":0},{"callOption":"2026-07-02_7.50_Call","callPrice":0.1,"callDelta":0.09,"callVolume":3,"callIv":100.91,"callOi":424,"putOption":"2026-07-02_7.50_Put","putPrice":2.68,"putDelta":-0.91,"putVolume":0,"putIv":144.9,"putOi":85},{"callOption":"2026-07-02_7.00_Call","callPrice":0.11,"callDelta":0.15,"callVolume":80,"callIv":103.95,"callOi":1572,"putOption":"2026-07-02_7.00_Put","putPrice":2.22,"putDelta":-0.85,"putVolume":0,"putIv":0.0,"putOi":30},{"callOption":"2026-07-02_6.50_Call","callPrice":0.15,"callDelta":0.21,"callVolume":3,"callIv":99.28,"callOi":1766,"putOption":"2026-07-02_6.50_Put","putPrice":1.68,"putDelta":-0.79,"putVolume":0,"putIv":125.94,"putOi":109},{"callOption":"2026-07-02_6.00_Call","callPrice":0.23,"callDelta":0.29,"callVolume":112,"callIv":98.15,"callOi":1499,"putOption":"2026-07-02_6.00_Put","putPrice":0.96,"putDelta":-0.71,"putVolume":0,"putIv":89.37,"putOi":13},{"callOption":"2026-07-02_5.50_Call","callPrice":0.37,"callDelta":0.39,"callVolume":5,"callIv":88.13,"callOi":913,"putOption":"2026-07-02_5.50_Put","putPrice":0.94,"putDelta":-0.61,"putVolume":0,"putIv":95.42,"putOi":321},{"callOption":"2026-07-02_5.00_Call","callPrice":0.49,"callDelta":0.55,"callVolume":31,"callIv":90.67,"callOi":907,"putOption":"2026-07-02_5.00_Put","putPrice":0.51,"putDelta":-0.45,"putVolume":10,"putIv":101.33,"putOi":558},{"callOption":"2026-07-02_4.50_Call","callPrice":0.72,"callDelta":0.68,"callVolume":0,"callIv":43.85,"callOi":303,"putOption":"2026-07-02_4.50_Put","putPrice":0.23,"putDelta":-0.31,"putVolume":1,"putIv":102.75,"putOi":459},{"callOption":"2026-07-02_4.00_Call","callPrice":1.0,"callDelta":0.77,"callVolume":0,"callIv":101.8,"callOi":164,"putOption":"2026-07-02_4.00_Put","putPrice":0.13,"putDelta":-0.23,"putVolume":0,"putIv":96.45,"putOi":301},{"callOption":"2026-07-02_3.50_Call","callPrice":1.5,"callDelta":0.85,"callVolume":0,"callIv":229.54,"callOi":166,"putOption":"2026-07-02_3.50_Put","putPrice":0.07,"putDelta":-0.15,"putVolume":0,"putIv":205.1,"putOi":3},{"callOption":"2026-07-02_3.00_Call","callPrice":1.95,"callDelta":0.92,"callVolume":0,"callIv":151.23,"callOi":124,"putOption":"2026-07-02_3.00_Put","putPrice":0.04,"putDelta":-0.08,"putVolume":0,"putIv":258.98,"putOi":12},{"callOption":"2026-07-02_2.50_Call","callPrice":2.44,"callDelta":0.96,"callVolume":0,"callIv":0.0,"callOi":0,"putOption":"2026-07-02_2.50_Put","putPrice":0.38,"putDelta":-0.11,"putVolume":0,"putIv":324.99,"putOi":0},{"callOption":"2026-07-02_2.00_Call","callPrice":2.5,"callDelta":0.99,"callVolume":0,"callIv":0.0,"callOi":1,"putOption":"2026-07-02_2.00_Put","putPrice":0.38,"putDelta":-0.08,"putVolume":0,"putIv":404.11,"putOi":0},{"callOption":"2026-07-02_1.50_Call","callPrice":3.75,"callDelta":0.94,"callVolume":0,"callIv":448.19,"callOi":0,"putOption":"2026-07-02_1.50_Put","putPrice":0.38,"putDelta":-0.06,"putVolume":0,"putIv":516.28,"putOi":0},{"callOption":"2026-07-02_1.00_Call","callPrice":4.5,"callDelta":1.0,"callVolume":0,"callIv":0.0,"callOi":50,"putOption":"2026-07-02_1.00_Put","putPrice":0.38,"putDelta":-0.04,"putVolume":0,"putIv":700.09,"putOi":0},{"callOption":"2026-07-02_0.50_Call","callPrice":5.19,"callDelta":1.0,"callVolume":0,"callIv":1196.41,"callOi":260,"putOption":"2026-07-02_0.50_Put","putPrice":0.44,"putDelta":-0.01,"putVolume":0,"putIv":1441.67,"putOi":0},{"callOption":"2026-07-10_10.00_Call","callPrice":0.38,"callDelta":0.25,"callVolume":0,"callIv":218.45,"callOi":0,"putOption":"2026-07-10_10.00_Put","putPrice":5.15,"putDelta":-0.86,"putVolume":0,"putIv":166.6,"putOi":0},{"callOption":"2026-07-10_9.00_Call","callPrice":0.06,"callDelta":0.19,"callVolume":0,"callIv":124.55,"callOi":622,"putOption":"2026-07-10_9.00_Put","putPrice":4.15,"putDelta":-0.85,"putVolume":0,"putIv":149.08,"putOi":0},{"callOption":"2026-07-10_8.50_Call","callPrice":0.06,"callDelta":0.22,"callVolume":0,"callIv":112.07,"callOi":400,"putOption":"2026-07-10_8.50_Put","putPrice":3.65,"putDelta":-0.84,"putVolume":0,"putIv":139.29,"putOi":0},{"callOption":"2026-07-10_8.00_Call","callPrice":0.09,"callDelta":0.25,"callVolume":0,"callIv":167.6,"callOi":1235,"putOption":"2026-07-10_8.00_Put","putPrice":3.53,"putDelta":-0.66,"putVolume":0,"putIv":204.13,"putOi":0},{"callOption":"2026-07-10_7.50_Call","callPrice":0.08,"callDelta":0.17,"callVolume":1,"callIv":113.03,"callOi":46,"putOption":"2026-07-10_7.50_Put","putPrice":2.53,"putDelta":-0.83,"putVolume":0,"putIv":190.56,"putOi":4},{"callOption":"2026-07-10_7.00_Call","callPrice":0.12,"callDelta":0.35,"callVolume":0,"callIv":142.59,"callOi":1854,"putOption":"2026-07-10_7.00_Put","putPrice":2.2,"putDelta":-0.65,"putVolume":0,"putIv":136.27,"putOi":5},{"callOption":"2026-07-10_6.50_Call","callPrice":0.25,"callDelta":0.4,"callVolume":0,"callIv":136.97,"callOi":1638,"putOption":"2026-07-10_6.50_Put","putPrice":1.69,"putDelta":-0.6,"putVolume":0,"putIv":225.69,"putOi":65},{"callOption":"2026-07-10_6.00_Call","callPrice":0.3,"callDelta":0.46,"callVolume":0,"callIv":91.84,"callOi":395,"putOption":"2026-07-10_6.00_Put","putPrice":0.84,"putDelta":-0.54,"putVolume":0,"putIv":0.0,"putOi":1},{"callOption":"2026-07-10_5.50_Call","callPrice":0.39,"callDelta":0.43,"callVolume":10,"callIv":95.54,"callOi":404,"putOption":"2026-07-10_5.50_Put","putPrice":0.99,"putDelta":-0.57,"putVolume":0,"putIv":133.93,"putOi":72},{"callOption":"2026-07-10_5.00_Call","callPrice":0.78,"callDelta":0.56,"callVolume":8,"callIv":99.87,"callOi":253,"putOption":"2026-07-10_5.00_Put","putPrice":0.68,"putDelta":-0.44,"putVolume":0,"putIv":76.78,"putOi":149},{"callOption":"2026-07-10_4.50_Call","callPrice":0.78,"callDelta":0.68,"callVolume":0,"callIv":39.13,"callOi":51,"putOption":"2026-07-10_4.50_Put","putPrice":0.36,"putDelta":-0.32,"putVolume":0,"putIv":133.97,"putOi":263},{"callOption":"2026-07-10_4.00_Call","callPrice":1.07,"callDelta":0.76,"callVolume":0,"callIv":165.99,"callOi":63,"putOption":"2026-07-10_4.00_Put","putPrice":0.18,"putDelta":-0.24,"putVolume":0,"putIv":95.12,"putOi":41},{"callOption":"2026-07-10_3.50_Call","callPrice":1.68,"callDelta":0.86,"callVolume":0,"callIv":131.32,"callOi":0,"putOption":"2026-07-10_3.50_Put","putPrice":0.38,"putDelta":-0.18,"putVolume":0,"putIv":181.13,"putOi":0},{"callOption":"2026-07-10_3.00_Call","callPrice":1.95,"callDelta":0.9,"callVolume":0,"callIv":0.0,"callOi":0,"putOption":"2026-07-10_3.00_Put","putPrice":0.05,"putDelta":-0.1,"putVolume":0,"putIv":228.65,"putOi":5},{"callOption":"2026-07-10_2.50_Call","callPrice":2.47,"callDelta":0.95,"callVolume":0,"callIv":0.0,"callOi":0,"putOption":"2026-07-10_2.50_Put","putPrice":0.38,"putDelta":-0.11,"putVolume":0,"putIv":285.18,"putOi":0},{"callOption":"2026-07-10_2.00_Call","callPrice":3.6,"callDelta":0.98,"callVolume":0,"callIv":0.0,"callOi":1,"putOption":"2026-07-10_2.00_Put","putPrice":0.38,"putDelta":-0.08,"putVolume":0,"putIv":356.65,"putOi":0},{"callOption":"2026-07-10_1.50_Call","callPrice":4.06,"callDelta":1.0,"callVolume":0,"callIv":0.0,"callOi":6,"putOption":"2026-07-10_1.50_Put","putPrice":0.38,"putDelta":-0.06,"putVolume":0,"putIv":455.6,"putOi":0},{"callOption":"2026-07-10_1.00_Call","callPrice":4.6,"callDelta":1.0,"callVolume":0,"callIv":0.0,"callOi":1,"putOption":"2026-07-10_1.00_Put","putPrice":0.38,"putDelta":-0.04,"putVolume":0,"putIv":617.77,"putOi":0},{"callOption":"2026-07-17_10.00_Call","callPrice":0.07,"callDelta":0.07,"callVolume":18,"callIv":122.29,"callOi":7129,"putOption":"2026-07-17_10.00_Put","putPrice":5.05,"putDelta":-0.93,"putVolume":0,"putIv":201.25,"putOi":92},{"callOption":"2026-07-17_9.00_Call","callPrice":0.09,"callDelta":0.22,"callVolume":0,"callIv":118.8,"callOi":2221,"putOption":"2026-07-17_9.00_Put","putPrice":3.8,"putDelta":-0.78,"putVolume":0,"putIv":0.0,"putOi":137},{"callOption":"2026-07-17_8.00_Call","callPrice":0.12,"callDelta":0.15,"callVolume":52,"callIv":109.89,"callOi":3419,"putOption":"2026-07-17_8.00_Put","putPrice":2.9,"putDelta":-0.8,"putVolume":3,"putIv":129.59,"putOi":95},{"callOption":"2026-07-17_7.00_Call","callPrice":0.2,"callDelta":0.22,"callVolume":590,"callIv":103.26,"callOi":6791,"putOption":"2026-07-17_7.00_Put","putPrice":2.26,"putDelta":-0.78,"putVolume":0,"putIv":86.64,"putOi":230},{"callOption":"2026-07-17_6.00_Call","callPrice":0.33,"callDelta":0.35,"callVolume":205,"callIv":96.76,"callOi":12784,"putOption":"2026-07-17_6.00_Put","putPrice":1.41,"putDelta":-0.65,"putVolume":0,"putIv":117.27,"putOi":421},{"callOption":"2026-07-17_5.00_Call","callPrice":0.68,"callDelta":0.57,"callVolume":76,"callIv":94.87,"callOi":5721,"putOption":"2026-07-17_5.00_Put","putPrice":0.53,"putDelta":-0.45,"putVolume":3,"putIv":74.93,"putOi":1151},{"callOption":"2026-07-17_4.00_Call","callPrice":1.09,"callDelta":0.84,"callVolume":18,"callIv":76.41,"callOi":2343,"putOption":"2026-07-17_4.00_Put","putPrice":0.19,"putDelta":-0.2,"putVolume":19,"putIv":93.64,"putOi":2823},{"callOption":"2026-07-17_3.00_Call","callPrice":1.93,"callDelta":0.89,"callVolume":0,"callIv":98.37,"callOi":768,"putOption":"2026-07-17_3.00_Put","putPrice":0.02,"putDelta":-0.11,"putVolume":0,"putIv":100.34,"putOi":1218},{"callOption":"2026-07-17_2.00_Call","callPrice":2.58,"callDelta":0.97,"callVolume":0,"callIv":294.1,"callOi":3,"putOption":"2026-07-17_2.00_Put","putPrice":0.38,"putDelta":-0.08,"putVolume":0,"putIv":326.53,"putOi":0},{"callOption":"2026-07-17_1.00_Call","callPrice":4.69,"callDelta":1.0,"callVolume":0,"callIv":0.0,"callOi":2,"putOption":"2026-07-17_1.00_Put","putPrice":0.03,"putDelta":-0.01,"putVolume":0,"putIv":257.98,"putOi":0},{"callOption":"2026-07-24_9.00_Call","callPrice":1.11,"callDelta":0.47,"callVolume":0,"callIv":274.67,"callOi":0,"putOption":"2026-07-24_9.00_Put","putPrice":4.13,"putDelta":-0.86,"putVolume":0,"putIv":122.16,"putOi":0},{"callOption":"2026-07-24_8.50_Call","callPrice":1.12,"callDelta":0.48,"callVolume":0,"callIv":266.2,"callOi":0,"putOption":"2026-07-24_8.50_Put","putPrice":3.64,"putDelta":-0.85,"putVolume":0,"putIv":116.31,"putOi":0},{"callOption":"2026-07-24_8.00_Call","callPrice":1.04,"callDelta":0.47,"callVolume":0,"callIv":244.57,"callOi":0,"putOption":"2026-07-24_8.00_Put","putPrice":3.17,"putDelta":-0.82,"putVolume":0,"putIv":114.84,"putOi":0},{"callOption":"2026-07-24_7.50_Call","callPrice":1.15,"callDelta":0.51,"callVolume":0,"callIv":247.7,"callOi":0,"putOption":"2026-07-24_7.50_Put","putPrice":2.72,"putDelta":-0.78,"putVolume":0,"putIv":113.22,"putOi":0},{"callOption":"2026-07-24_7.00_Call","callPrice":1.18,"callDelta":0.52,"callVolume":0,"callIv":237.93,"callOi":0,"putOption":"2026-07-24_7.00_Put","putPrice":2.31,"putDelta":-0.71,"putVolume":0,"putIv":117.42,"putOi":0},{"callOption":"2026-07-24_6.50_Call","callPrice":1.21,"callDelta":0.54,"callVolume":0,"callIv":227.18,"callOi":0,"putOption":"2026-07-24_6.50_Put","putPrice":1.96,"putDelta":-0.63,"putVolume":0,"putIv":125.85,"putOi":0},{"callOption":"2026-07-24_6.00_Call","callPrice":1.26,"callDelta":0.57,"callVolume":0,"callIv":217.09,"callOi":0,"putOption":"2026-07-24_6.00_Put","putPrice":1.75,"putDelta":-0.52,"putVolume":0,"putIv":149.06,"putOi":0},{"callOption":"2026-07-24_5.50_Call","callPrice":0.93,"callDelta":0.6,"callVolume":1,"callIv":206.38,"callOi":0,"putOption":"2026-07-24_5.50_Put","putPrice":1.58,"putDelta":-0.43,"putVolume":0,"putIv":173.01,"putOi":0},{"callOption":"2026-07-24_5.00_Call","callPrice":1.4,"callDelta":0.64,"callVolume":0,"callIv":193.49,"callOi":0,"putOption":"2026-07-24_5.00_Put","putPrice":1.4,"putDelta":-0.36,"putVolume":0,"putIv":193.98,"putOi":0},{"callOption":"2026-07-24_4.50_Call","callPrice":0.88,"callDelta":0.69,"callVolume":0,"callIv":84.87,"callOi":0,"putOption":"2026-07-24_4.50_Put","putPrice":1.27,"putDelta":-0.3,"putVolume":0,"putIv":222.05,"putOi":0},{"callOption":"2026-07-24_4.00_Call","callPrice":1.65,"callDelta":0.75,"callVolume":0,"callIv":166.0,"callOi":0,"putOption":"2026-07-24_4.00_Put","putPrice":1.17,"putDelta":-0.24,"putVolume":0,"putIv":255.07,"putOi":0},{"callOption":"2026-07-24_3.50_Call","callPrice":1.83,"callDelta":0.83,"callVolume":0,"callIv":144.14,"callOi":0,"putOption":"2026-07-24_3.50_Put","putPrice":1.11,"putDelta":-0.19,"putVolume":0,"putIv":298.77,"putOi":0},{"callOption":"2026-07-24_3.00_Call","callPrice":2.13,"callDelta":0.91,"callVolume":0,"callIv":128.52,"callOi":0,"putOption":"2026-07-24_3.00_Put","putPrice":1.08,"putDelta":-0.15,"putVolume":0,"putIv":356.7,"putOi":0},{"callOption":"2026-07-24_2.50_Call","callPrice":2.47,"callDelta":0.93,"callVolume":0,"callIv":0.0,"callOi":0,"putOption":"2026-07-24_2.50_Put","putPrice":1.07,"putDelta":-0.11,"putVolume":0,"putIv":435.48,"putOi":0},{"callOption":"2026-07-24_2.00_Call","callPrice":2.97,"callDelta":0.97,"callVolume":0,"callIv":0.0,"callOi":0,"putOption":"2026-07-24_2.00_Put","putPrice":1.07,"putDelta":-0.07,"putVolume":0,"putIv":548.15,"putOi":0},{"callOption":"2026-07-24_1.50_Call","callPrice":3.47,"callDelta":0.99,"callVolume":0,"callIv":0.0,"callOi":0,"putOption":"2026-07-24_1.50_Put","putPrice":1.07,"putDelta":-0.03,"putVolume":0,"putIv":747.0,"putOi":0},{"callOption":"2026-07-24_1.00_Call","callPrice":3.96,"callDelta":1.0,"callVolume":0,"callIv":0.0,"callOi":0,"putOption":"2026-07-24_1.00_Put","putPrice":1.07,"putDelta":0.0,"putVolume":0,"putIv":0.0,"putOi":0},{"callOption":"2026-08-21_13.00_Call","callPrice":0.08,"callDelta":0.1,"callVolume":13,"callIv":131.79,"callOi":971,"putOption":"2026-08-21_13.00_Put","putPrice":8.38,"putDelta":-0.87,"putVolume":0,"putIv":146.99,"putOi":0},{"callOption":"2026-08-21_12.00_Call","callPrice":0.15,"callDelta":0.11,"callVolume":1,"callIv":122.84,"callOi":1231,"putOption":"2026-08-21_12.00_Put","putPrice":7.73,"putDelta":-0.89,"putVolume":0,"putIv":143.03,"putOi":34},{"callOption":"2026-08-21_11.00_Call","callPrice":0.15,"callDelta":0.25,"callVolume":0,"callIv":123.74,"callOi":1072,"putOption":"2026-08-21_11.00_Put","putPrice":6.65,"putDelta":-0.75,"putVolume":0,"putIv":133.17,"putOi":435},{"callOption":"2026-08-21_10.00_Call","callPrice":0.17,"callDelta":0.14,"callVolume":127,"callIv":111.71,"callOi":17925,"putOption":"2026-08-21_10.00_Put","putPrice":5.25,"putDelta":-0.86,"putVolume":0,"putIv":130.49,"putOi":320},{"callOption":"2026-08-21_9.00_Call","callPrice":0.2,"callDelta":0.2,"callVolume":472,"callIv":115.21,"callOi":3784,"putOption":"2026-08-21_9.00_Put","putPrice":3.75,"putDelta":-0.8,"putVolume":0,"putIv":125.06,"putOi":41},{"callOption":"2026-08-21_8.00_Call","callPrice":0.31,"callDelta":0.24,"callVolume":14,"callIv":107.21,"callOi":10647,"putOption":"2026-08-21_8.00_Put","putPrice":3.3,"putDelta":-0.76,"putVolume":0,"putIv":116.41,"putOi":438},{"callOption":"2026-08-21_7.00_Call","callPrice":0.41,"callDelta":0.32,"callVolume":102,"callIv":103.62,"callOi":27922,"putOption":"2026-08-21_7.00_Put","putPrice":2.29,"putDelta":-0.68,"putVolume":0,"putIv":114.34,"putOi":3206},{"callOption":"2026-08-21_6.00_Call","callPrice":0.63,"callDelta":0.45,"callVolume":104,"callIv":103.3,"callOi":14552,"putOption":"2026-08-21_6.00_Put","putPrice":1.63,"putDelta":-0.55,"putVolume":0,"putIv":108.95,"putOi":5841},{"callOption":"2026-08-21_5.00_Call","callPrice":0.93,"callDelta":0.6,"callVolume":5,"callIv":100.73,"callOi":22445,"putOption":"2026-08-21_5.00_Put","putPrice":0.95,"putDelta":-0.4,"putVolume":0,"putIv":105.95,"putOi":10534},{"callOption":"2026-08-21_4.00_Call","callPrice":1.38,"callDelta":0.77,"callVolume":1,"callIv":93.83,"callOi":2506,"putOption":"2026-08-21_4.00_Put","putPrice":0.4,"putDelta":-0.24,"putVolume":10,"putIv":98.9,"putOi":4456},{"callOption":"2026-08-21_3.00_Call","callPrice":2.0,"callDelta":0.86,"callVolume":0,"callIv":73.18,"callOi":1152,"putOption":"2026-08-21_3.00_Put","putPrice":0.15,"putDelta":-0.14,"putVolume":0,"putIv":102.07,"putOi":1405},{"callOption":"2026-08-21_2.00_Call","callPrice":3.0,"callDelta":0.95,"callVolume":0,"callIv":0.0,"callOi":769,"putOption":"2026-08-21_2.00_Put","putPrice":0.04,"putDelta":-0.05,"putVolume":0,"putIv":132.83,"putOi":744},{"callOption":"2026-08-21_1.00_Call","callPrice":4.69,"callDelta":0.99,"callVolume":0,"callIv":316.62,"callOi":67,"putOption":"2026-08-21_1.00_Put","putPrice":0.02,"putDelta":-0.01,"putVolume":0,"putIv":175.8,"putOi":24},{"callOption":"2026-08-21_15.00_Call","callPrice":0.07,"callDelta":0.05,"callVolume":3,"callIv":125.36,"callOi":2672,"putOption":"2026-08-21_15.00_Put","putPrice":10.6,"putDelta":-0.89,"putVolume":0,"putIv":156.86,"putOi":0},{"callOption":"2026-08-21_14.00_Call","callPrice":0.08,"callDelta":0.09,"callVolume":10,"callIv":135.0,"callOi":422,"putOption":"2026-08-21_14.00_Put","putPrice":8.7,"putDelta":-0.88,"putVolume":0,"putIv":149.56,"putOi":0},{"callOption":"2026-09-18_15.00_Call","callPrice":0.15,"callDelta":0.1,"callVolume":26,"callIv":125.44,"callOi":7554,"putOption":"2026-09-18_15.00_Put","putPrice":9.8,"putDelta":-0.9,"putVolume":0,"putIv":132.7,"putOi":4},{"callOption":"2026-09-18_12.00_Call","callPrice":0.16,"callDelta":0.15,"callVolume":100,"callIv":118.58,"callOi":1053,"putOption":"2026-09-18_12.00_Put","putPrice":6.9,"putDelta":-0.85,"putVolume":0,"putIv":125.19,"putOi":4},{"callOption":"2026-09-18_10.00_Call","callPrice":0.28,"callDelta":0.21,"callVolume":111,"callIv":114.36,"callOi":13421,"putOption":"2026-09-18_10.00_Put","putPrice":4.95,"putDelta":-0.79,"putVolume":0,"putIv":120.45,"putOi":1567},{"callOption":"2026-09-18_9.00_Call","callPrice":0.33,"callDelta":0.24,"callVolume":2,"callIv":109.15,"callOi":1726,"putOption":"2026-09-18_9.00_Put","putPrice":4.0,"putDelta":-0.76,"putVolume":0,"putIv":117.83,"putOi":26},{"callOption":"2026-09-18_8.00_Call","callPrice":0.43,"callDelta":0.46,"callVolume":0,"callIv":108.9,"callOi":3647,"putOption":"2026-09-18_8.00_Put","putPrice":3.3,"putDelta":-0.54,"putVolume":0,"putIv":112.14,"putOi":121},{"callOption":"2026-09-18_7.00_Call","callPrice":0.55,"callDelta":0.39,"callVolume":29,"callIv":106.05,"callOi":7436,"putOption":"2026-09-18_7.00_Put","putPrice":2.27,"putDelta":-0.61,"putVolume":0,"putIv":108.6,"putOi":4511},{"callOption":"2026-09-18_6.00_Call","callPrice":0.82,"callDelta":0.48,"callVolume":11,"callIv":100.4,"callOi":3848,"putOption":"2026-09-18_6.00_Put","putPrice":1.77,"putDelta":-0.51,"putVolume":2,"putIv":105.58,"putOi":1825},{"callOption":"2026-09-18_5.00_Call","callPrice":1.05,"callDelta":0.61,"callVolume":28,"callIv":97.95,"callOi":6834,"putOption":"2026-09-18_5.00_Put","putPrice":1.05,"putDelta":-0.39,"putVolume":5,"putIv":102.68,"putOi":6921},{"callOption":"2026-09-18_4.00_Call","callPrice":1.54,"callDelta":0.76,"callVolume":0,"callIv":96.63,"callOi":2448,"putOption":"2026-09-18_4.00_Put","putPrice":0.5,"putDelta":-0.24,"putVolume":0,"putIv":94.93,"putOi":2663},{"callOption":"2026-09-18_3.00_Call","callPrice":2.52,"callDelta":0.85,"callVolume":0,"callIv":77.75,"callOi":720,"putOption":"2026-09-18_3.00_Put","putPrice":0.18,"putDelta":-0.15,"putVolume":0,"putIv":93.34,"putOi":365},{"callOption":"2026-09-18_2.00_Call","callPrice":3.25,"callDelta":0.93,"callVolume":0,"callIv":0.0,"callOi":391,"putOption":"2026-09-18_2.00_Put","putPrice":0.06,"putDelta":-0.07,"putVolume":0,"putIv":116.56,"putOi":1441},{"callOption":"2026-09-18_1.00_Call","callPrice":4.2,"callDelta":0.99,"callVolume":0,"callIv":174.99,"callOi":32,"putOption":"2026-09-18_1.00_Put","putPrice":0.05,"putDelta":-0.01,"putVolume":0,"putIv":185.2,"putOi":14},{"callOption":"2026-09-18_14.00_Call","callPrice":0.1,"callDelta":0.23,"callVolume":0,"callIv":125.76,"callOi":544,"putOption":"2026-09-18_14.00_Put","putPrice":9.15,"putDelta":-0.87,"putVolume":0,"putIv":135.93,"putOi":0},{"callOption":"2026-09-18_13.00_Call","callPrice":0.18,"callDelta":0.26,"callVolume":0,"callIv":123.07,"callOi":150,"putOption":"2026-09-18_13.00_Put","putPrice":8.6,"putDelta":-0.74,"putVolume":0,"putIv":133.01,"putOi":13},{"callOption":"2026-09-18_11.00_Call","callPrice":0.18,"callDelta":0.18,"callVolume":7,"callIv":116.72,"callOi":798,"putOption":"2026-09-18_11.00_Put","putPrice":6.23,"putDelta":-0.81,"putVolume":0,"putIv":123.84,"putOi":0},{"callOption":"2026-10-16_10.00_Call","callPrice":0.35,"callDelta":0.25,"callVolume":12,"callIv":110.24,"callOi":3037,"putOption":"2026-10-16_10.00_Put","putPrice":5.35,"putDelta":-0.74,"putVolume":0,"putIv":116.82,"putOi":0},{"callOption":"2026-10-16_9.00_Call","callPrice":0.5,"callDelta":0.46,"callVolume":0,"callIv":107.43,"callOi":754,"putOption":"2026-10-16_9.00_Put","putPrice":4.43,"putDelta":-0.7,"putVolume":0,"putIv":113.6,"putOi":0},{"callOption":"2026-10-16_8.00_Call","callPrice":0.58,"callDelta":0.51,"callVolume":0,"callIv":104.39,"callOi":235,"putOption":"2026-10-16_8.00_Put","putPrice":3.55,"putDelta":-0.49,"putVolume":0,"putIv":110.09,"putOi":61},{"callOption":"2026-10-16_7.00_Call","callPrice":0.72,"callDelta":0.56,"callVolume":0,"callIv":102.14,"callOi":603,"putOption":"2026-10-16_7.00_Put","putPrice":2.68,"putDelta":-0.44,"putVolume":0,"putIv":102.31,"putOi":11},{"callOption":"2026-10-16_6.00_Call","callPrice":0.85,"callDelta":0.63,"callVolume":0,"callIv":98.88,"callOi":908,"putOption":"2026-10-16_6.00_Put","putPrice":1.75,"putDelta":-0.37,"putVolume":0,"putIv":96.78,"putOi":26},{"callOption":"2026-10-16_5.00_Call","callPrice":1.22,"callDelta":0.63,"callVolume":6,"callIv":108.88,"callOi":614,"putOption":"2026-10-16_5.00_Put","putPrice":1.17,"putDelta":-0.37,"putVolume":0,"putIv":102.38,"putOi":327},{"callOption":"2026-10-16_4.00_Call","callPrice":1.6,"callDelta":0.75,"callVolume":4,"callIv":97.98,"callOi":674,"putOption":"2026-10-16_4.00_Put","putPrice":0.62,"putDelta":-0.25,"putVolume":0,"putIv":100.7,"putOi":46},{"callOption":"2026-10-16_3.00_Call","callPrice":2.16,"callDelta":0.85,"callVolume":0,"callIv":84.31,"callOi":156,"putOption":"2026-10-16_3.00_Put","putPrice":0.23,"putDelta":-0.15,"putVolume":0,"putIv":99.02,"putOi":77},{"callOption":"2026-10-16_2.00_Call","callPrice":2.99,"callDelta":0.93,"callVolume":0,"callIv":124.0,"callOi":94,"putOption":"2026-10-16_2.00_Put","putPrice":0.07,"putDelta":-0.04,"putVolume":0,"putIv":107.85,"putOi":0},{"callOption":"2026-10-16_1.00_Call","callPrice":4.1,"callDelta":0.97,"callVolume":0,"callIv":203.55,"callOi":0,"putOption":"2026-10-16_1.00_Put","putPrice":0.05,"putDelta":-0.02,"putVolume":0,"putIv":168.79,"putOi":0},{"callOption":"2026-11-20_11.00_Call","callPrice":0.64,"callDelta":0.44,"callVolume":0,"callIv":112.87,"callOi":323,"putOption":"2026-11-20_11.00_Put","putPrice":6.38,"putDelta":-0.73,"putVolume":0,"putIv":116.5,"putOi":0},{"callOption":"2026-11-20_9.00_Call","callPrice":0.59,"callDelta":0.35,"callVolume":33,"callIv":110.66,"callOi":7021,"putOption":"2026-11-20_9.00_Put","putPrice":4.74,"putDelta":-0.65,"putVolume":0,"putIv":112.96,"putOi":11},{"callOption":"2026-11-20_15.00_Call","callPrice":0.23,"callDelta":0.17,"callVolume":160,"callIv":118.58,"callOi":10380,"putOption":"2026-11-20_15.00_Put","putPrice":9.28,"putDelta":-0.83,"putVolume":0,"putIv":127.27,"putOi":132},{"callOption":"2026-11-20_12.00_Call","callPrice":0.31,"callDelta":0.23,"callVolume":5,"callIv":112.11,"callOi":7083,"putOption":"2026-11-20_12.00_Put","putPrice":7.1,"putDelta":-0.77,"putVolume":0,"putIv":119.36,"putOi":10},{"callOption":"2026-11-20_10.00_Call","callPrice":0.45,"callDelta":0.3,"callVolume":57,"callIv":110.76,"callOi":8077,"putOption":"2026-11-20_10.00_Put","putPrice":5.15,"putDelta":-0.7,"putVolume":0,"putIv":116.68,"putOi":142},{"callOption":"2026-11-20_7.00_Call","callPrice":0.83,"callDelta":0.6,"callVolume":0,"callIv":105.18,"callOi":3523,"putOption":"2026-11-20_7.00_Put","putPrice":2.83,"putDelta":-0.4,"putVolume":0,"putIv":108.34,"putOi":1928},{"callOption":"2026-11-20_5.00_Call","callPrice":1.39,"callDelta":0.64,"callVolume":16,"callIv":101.16,"callOi":5187,"putOption":"2026-11-20_5.00_Put","putPrice":1.28,"putDelta":-0.36,"putVolume":0,"putIv":104.03,"putOi":2371},{"callOption":"2026-11-20_4.00_Call","callPrice":1.68,"callDelta":0.78,"callVolume":0,"callIv":95.46,"callOi":9165,"putOption":"2026-11-20_4.00_Put","putPrice":0.75,"putDelta":-0.25,"putVolume":4,"putIv":102.35,"putOi":1503},{"callOption":"2026-11-20_3.00_Call","callPrice":2.26,"callDelta":0.85,"callVolume":0,"callIv":91.53,"callOi":308,"putOption":"2026-11-20_3.00_Put","putPrice":0.32,"putDelta":-0.15,"putVolume":0,"putIv":101.19,"putOi":413},{"callOption":"2026-11-20_2.00_Call","callPrice":2.9,"callDelta":0.92,"callVolume":0,"callIv":74.88,"callOi":293,"putOption":"2026-11-20_2.00_Put","putPrice":0.09,"putDelta":-0.08,"putVolume":0,"putIv":104.2,"putOi":271},{"callOption":"2026-11-20_1.00_Call","callPrice":4.45,"callDelta":0.98,"callVolume":0,"callIv":208.67,"callOi":150,"putOption":"2026-11-20_1.00_Put","putPrice":0.02,"putDelta":-0.02,"putVolume":0,"putIv":150.61,"putOi":301},{"callOption":"2026-11-20_8.00_Call","callPrice":0.68,"callDelta":0.56,"callVolume":0,"callIv":105.18,"callOi":1485,"putOption":"2026-11-20_8.00_Put","putPrice":3.55,"putDelta":-0.44,"putVolume":0,"putIv":111.0,"putOi":19},{"callOption":"2026-11-20_6.00_Call","callPrice":1.13,"callDelta":0.54,"callVolume":12,"callIv":102.44,"callOi":3771,"putOption":"2026-11-20_6.00_Put","putPrice":1.77,"putDelta":-0.46,"putVolume":0,"putIv":102.26,"putOi":2377},{"callOption":"2026-12-18_10.00_Call","callPrice":0.51,"callDelta":0.33,"callVolume":321,"callIv":109.25,"callOi":3084,"putOption":"2026-12-18_10.00_Put","putPrice":5.53,"putDelta":-0.67,"putVolume":0,"putIv":113.33,"putOi":0},{"callOption":"2026-12-18_9.00_Call","callPrice":0.64,"callDelta":0.37,"callVolume":6,"callIv":108.05,"callOi":137,"putOption":"2026-12-18_9.00_Put","putPrice":4.65,"putDelta":-0.62,"putVolume":0,"putIv":113.21,"putOi":0},{"callOption":"2026-12-18_8.00_Call","callPrice":0.85,"callDelta":0.59,"callVolume":0,"callIv":106.27,"callOi":1119,"putOption":"2026-12-18_8.00_Put","putPrice":3.49,"putDelta":-0.41,"putVolume":0,"putIv":109.2,"putOi":8},{"callOption":"2026-12-18_7.00_Call","callPrice":0.95,"callDelta":0.63,"callVolume":0,"callIv":106.01,"callOi":303,"putOption":"2026-12-18_7.00_Put","putPrice":2.97,"putDelta":-0.37,"putVolume":0,"putIv":108.17,"putOi":135},{"callOption":"2026-12-18_6.00_Call","callPrice":1.22,"callDelta":0.57,"callVolume":7,"callIv":106.62,"callOi":788,"putOption":"2026-12-18_6.00_Put","putPrice":2.14,"putDelta":-0.43,"putVolume":0,"putIv":104.84,"putOi":97},{"callOption":"2026-12-18_5.00_Call","callPrice":1.52,"callDelta":0.65,"callVolume":2,"callIv":100.6,"callOi":432,"putOption":"2026-12-18_5.00_Put","putPrice":1.29,"putDelta":-0.35,"putVolume":0,"putIv":103.26,"putOi":41},{"callOption":"2026-12-18_4.00_Call","callPrice":1.81,"callDelta":0.79,"callVolume":0,"callIv":95.65,"callOi":445,"putOption":"2026-12-18_4.00_Put","putPrice":0.83,"putDelta":-0.21,"putVolume":0,"putIv":101.37,"putOi":524},{"callOption":"2026-12-18_3.00_Call","callPrice":2.32,"callDelta":0.85,"callVolume":0,"callIv":89.77,"callOi":94,"putOption":"2026-12-18_3.00_Put","putPrice":0.45,"putDelta":-0.14,"putVolume":2,"putIv":100.32,"putOi":222},{"callOption":"2026-12-18_2.00_Call","callPrice":3.14,"callDelta":0.92,"callVolume":0,"callIv":90.94,"callOi":9,"putOption":"2026-12-18_2.00_Put","putPrice":0.14,"putDelta":-0.08,"putVolume":0,"putIv":100.77,"putOi":39},{"callOption":"2026-12-18_1.00_Call","callPrice":3.26,"callDelta":0.98,"callVolume":0,"callIv":192.42,"callOi":1,"putOption":"2026-12-18_1.00_Put","putPrice":0.04,"putDelta":-0.01,"putVolume":0,"putIv":129.71,"putOi":0},{"callOption":"2027-01-15_9.00_Call","callPrice":0.76,"callDelta":0.39,"callVolume":9,"callIv":105.89,"callOi":2012,"putOption":"2027-01-15_9.00_Put","putPrice":4.74,"putDelta":-0.61,"putVolume":0,"putIv":110.26,"putOi":2},{"callOption":"2027-01-15_8.00_Call","callPrice":0.94,"callDelta":0.45,"callVolume":16,"callIv":106.01,"callOi":1914,"putOption":"2027-01-15_8.00_Put","putPrice":3.6,"putDelta":-0.55,"putVolume":0,"putIv":114.42,"putOi":135},{"callOption":"2027-01-15_6.00_Call","callPrice":1.3,"callDelta":0.59,"callVolume":33,"callIv":107.64,"callOi":6371,"putOption":"2027-01-15_6.00_Put","putPrice":2.26,"putDelta":-0.41,"putVolume":0,"putIv":104.6,"putOi":558},{"callOption":"2027-01-15_15.00_Call","callPrice":0.47,"callDelta":0.24,"callVolume":20,"callIv":118.07,"callOi":13373,"putOption":"2027-01-15_15.00_Put","putPrice":10.3,"putDelta":-0.76,"putVolume":0,"putIv":120.99,"putOi":549},{"callOption":"2027-01-15_12.00_Call","callPrice":0.57,"callDelta":0.29,"callVolume":28,"callIv":110.96,"callOi":4249,"putOption":"2027-01-15_12.00_Put","putPrice":7.2,"putDelta":-0.71,"putVolume":0,"putIv":114.38,"putOi":75},{"callOption":"2027-01-15_10.00_Call","callPrice":0.72,"callDelta":0.37,"callVolume":384,"callIv":111.68,"callOi":42714,"putOption":"2027-01-15_10.00_Put","putPrice":5.6,"putDelta":-0.63,"putVolume":0,"putIv":112.4,"putOi":583},{"callOption":"2027-01-15_7.00_Call","callPrice":1.11,"callDelta":0.51,"callVolume":175,"callIv":105.97,"callOi":51301,"putOption":"2027-01-15_7.00_Put","putPrice":2.8,"putDelta":-0.49,"putVolume":0,"putIv":110.64,"putOi":8604},{"callOption":"2027-01-15_5.00_Call","callPrice":1.65,"callDelta":0.67,"callVolume":94,"callIv":103.55,"callOi":24885,"putOption":"2027-01-15_5.00_Put","putPrice":1.53,"putDelta":-0.33,"putVolume":0,"putIv":100.96,"putOi":5168},{"callOption":"2027-01-15_4.00_Call","callPrice":2.0,"callDelta":0.76,"callVolume":70,"callIv":100.09,"callOi":5145,"putOption":"2027-01-15_4.00_Put","putPrice":0.82,"putDelta":-0.24,"putVolume":2,"putIv":100.97,"putOi":4494},{"callOption":"2027-01-15_3.00_Call","callPrice":2.46,"callDelta":0.85,"callVolume":0,"callIv":91.07,"callOi":2305,"putOption":"2027-01-15_3.00_Put","putPrice":0.45,"putDelta":-0.15,"putVolume":0,"putIv":99.89,"putOi":1926},{"callOption":"2027-01-15_2.00_Call","callPrice":3.15,"callDelta":0.96,"callVolume":1,"callIv":82.15,"callOi":760,"putOption":"2027-01-15_2.00_Put","putPrice":0.13,"putDelta":-0.04,"putVolume":0,"putIv":94.53,"putOi":238},{"callOption":"2027-01-15_1.00_Call","callPrice":4.4,"callDelta":0.97,"callVolume":0,"callIv":142.55,"callOi":787,"putOption":"2027-01-15_1.00_Put","putPrice":0.05,"putDelta":-0.01,"putVolume":50,"putIv":114.01,"putOi":462},{"callOption":"2027-12-17_15.00_Call","callPrice":1.17,"callDelta":0.68,"callVolume":0,"callIv":102.23,"callOi":4250,"putOption":"2027-12-17_15.00_Put","putPrice":10.85,"putDelta":-0.32,"putVolume":0,"putIv":105.43,"putOi":272},{"callOption":"2027-12-17_12.00_Call","callPrice":1.34,"callDelta":0.72,"callVolume":0,"callIv":100.56,"callOi":2562,"putOption":"2027-12-17_12.00_Put","putPrice":7.75,"putDelta":-0.28,"putVolume":0,"putIv":103.34,"putOi":15},{"callOption":"2027-12-17_10.00_Call","callPrice":1.6,"callDelta":0.56,"callVolume":3,"callIv":104.31,"callOi":7941,"putOption":"2027-12-17_10.00_Put","putPrice":5.85,"putDelta":-0.44,"putVolume":0,"putIv":101.96,"putOi":102},{"callOption":"2027-12-17_7.00_Call","callPrice":1.92,"callDelta":0.81,"callVolume":0,"callIv":99.72,"callOi":6282,"putOption":"2027-12-17_7.00_Put","putPrice":3.4,"putDelta":-0.19,"putVolume":0,"putIv":99.21,"putOi":511},{"callOption":"2027-12-17_5.00_Call","callPrice":2.44,"callDelta":0.76,"callVolume":15,"callIv":106.52,"callOi":8941,"putOption":"2027-12-17_5.00_Put","putPrice":2.13,"putDelta":-0.25,"putVolume":25,"putIv":104.38,"putOi":2057},{"callOption":"2027-12-17_4.00_Call","callPrice":2.68,"callDelta":0.87,"callVolume":0,"callIv":97.54,"callOi":551,"putOption":"2027-12-17_4.00_Put","putPrice":1.98,"putDelta":-0.13,"putVolume":0,"putIv":98.88,"putOi":3188},{"callOption":"2027-12-17_3.00_Call","callPrice":3.0,"callDelta":0.86,"callVolume":56,"callIv":101.92,"callOi":3064,"putOption":"2027-12-17_3.00_Put","putPrice":0.83,"putDelta":-0.14,"putVolume":0,"putIv":98.89,"putOi":1716},{"callOption":"2027-12-17_2.00_Call","callPrice":3.95,"callDelta":0.93,"callVolume":0,"callIv":95.55,"callOi":752,"putOption":"2027-12-17_2.00_Put","putPrice":0.38,"putDelta":-0.07,"putVolume":0,"putIv":99.3,"putOi":190},{"callOption":"2027-12-17_1.00_Call","callPrice":4.15,"callDelta":0.97,"callVolume":0,"callIv":97.0,"callOi":281,"putOption":"2027-12-17_1.00_Put","putPrice":0.1,"putDelta":-0.03,"putVolume":0,"putIv":101.67,"putOi":188},{"callOption":"2028-01-21_15.00_Call","callPrice":1.16,"callDelta":0.45,"callVolume":49,"callIv":103.02,"callOi":29642,"putOption":"2028-01-21_15.00_Put","putPrice":10.3,"putDelta":-0.55,"putVolume":0,"putIv":104.31,"putOi":296},{"callOption":"2028-01-21_12.00_Call","callPrice":1.4,"callDelta":0.74,"callVolume":0,"callIv":101.73,"callOi":3363,"putOption":"2028-01-21_12.00_Put","putPrice":7.95,"putDelta":-0.26,"putVolume":0,"putIv":102.1,"putOi":452},{"callOption":"2028-01-21_10.00_Call","callPrice":1.7,"callDelta":0.56,"callVolume":1,"callIv":101.22,"callOi":16723,"putOption":"2028-01-21_10.00_Put","putPrice":5.96,"putDelta":-0.44,"putVolume":0,"putIv":122.22,"putOi":516},{"callOption":"2028-01-21_7.00_Call","callPrice":2.04,"callDelta":0.68,"callVolume":2,"callIv":104.3,"callOi":14719,"putOption":"2028-01-21_7.00_Put","putPrice":3.9,"putDelta":-0.32,"putVolume":0,"putIv":121.14,"putOi":1245},{"callOption":"2028-01-21_5.00_Call","callPrice":2.36,"callDelta":0.77,"callVolume":9,"callIv":107.69,"callOi":23265,"putOption":"2028-01-21_5.00_Put","putPrice":2.32,"putDelta":-0.23,"putVolume":0,"putIv":103.73,"putOi":5217},{"callOption":"2028-01-21_4.00_Call","callPrice":2.82,"callDelta":0.88,"callVolume":0,"callIv":105.76,"callOi":4319,"putOption":"2028-01-21_4.00_Put","putPrice":1.52,"putDelta":-0.12,"putVolume":0,"putIv":99.11,"putOi":3646},{"callOption":"2028-01-21_3.00_Call","callPrice":3.3,"callDelta":0.9,"callVolume":0,"callIv":99.28,"callOi":2457,"putOption":"2028-01-21_3.00_Put","putPrice":0.95,"putDelta":-0.1,"putVolume":0,"putIv":98.72,"putOi":782},{"callOption":"2028-01-21_2.00_Call","callPrice":3.58,"callDelta":0.93,"callVolume":0,"callIv":102.85,"callOi":2106,"putOption":"2028-01-21_2.00_Put","putPrice":0.41,"putDelta":-0.07,"putVolume":0,"putIv":99.74,"putOi":236},{"callOption":"2028-01-21_1.00_Call","callPrice":4.1,"callDelta":0.97,"callVolume":0,"callIv":182.52,"callOi":2440,"putOption":"2028-01-21_1.00_Put","putPrice":0.11,"putDelta":-0.03,"putVolume":0,"putIv":109.88,"putOi":315}]}