{"header":{"callVolume":6161.0,"putVolume":1937.0,"cpRatio":3.18,"callOi":50351.0,"putOi":54611.0,"cputOiRatio":0.92,"underlyingPrice":41.07},"contracts":[{"callOption":"2026-07-17_32.50_Call","callPrice":8.6,"callDelta":0.98,"callVolume":0,"callIv":54.96,"callOi":0,"putOption":"2026-07-17_32.50_Put","putPrice":0.11,"putDelta":-0.02,"putVolume":0,"putIv":58.94,"putOi":61},{"callOption":"2026-07-17_35.00_Call","callPrice":6.1,"callDelta":0.94,"callVolume":1,"callIv":52.11,"callOi":11,"putOption":"2026-07-17_35.00_Put","putPrice":0.15,"putDelta":-0.07,"putVolume":362,"putIv":53.89,"putOi":16889},{"callOption":"2026-07-17_37.50_Call","callPrice":4.5,"callDelta":0.77,"callVolume":3,"callIv":65.99,"callOi":29,"putOption":"2026-07-17_37.50_Put","putPrice":0.41,"putDelta":-0.17,"putVolume":85,"putIv":48.44,"putOi":4687},{"callOption":"2026-07-17_52.50_Call","callPrice":0.05,"callDelta":0.04,"callVolume":2,"callIv":63.01,"callOi":620,"putOption":"2026-07-17_52.50_Put","putPrice":12.31,"putDelta":-0.93,"putVolume":0,"putIv":75.24,"putOi":0},{"callOption":"2026-07-17_57.50_Call","callPrice":0.12,"callDelta":0.01,"callVolume":0,"callIv":117.93,"callOi":73,"putOption":"2026-07-17_57.50_Put","putPrice":7.25,"putDelta":-0.99,"putVolume":0,"putIv":90.61,"putOi":1},{"callOption":"2026-07-17_42.50_Call","callPrice":1.07,"callDelta":0.39,"callVolume":3517,"callIv":49.3,"callOi":3483,"putOption":"2026-07-17_42.50_Put","putPrice":2.35,"putDelta":-0.6,"putVolume":39,"putIv":52.45,"putOi":436},{"callOption":"2026-07-17_40.00_Call","callPrice":2.3,"callDelta":0.62,"callVolume":429,"callIv":49.02,"callOi":6695,"putOption":"2026-07-17_40.00_Put","putPrice":1.05,"putDelta":-0.37,"putVolume":158,"putIv":46.75,"putOi":879},{"callOption":"2026-07-17_50.00_Call","callPrice":0.08,"callDelta":0.05,"callVolume":12,"callIv":55.71,"callOi":697,"putOption":"2026-07-17_50.00_Put","putPrice":11.8,"putDelta":-0.95,"putVolume":0,"putIv":0.0,"putOi":278},{"callOption":"2026-07-17_55.00_Call","callPrice":0.03,"callDelta":0.08,"callVolume":1,"callIv":91.35,"callOi":1479,"putOption":"2026-07-17_55.00_Put","putPrice":12.6,"putDelta":-0.92,"putVolume":5,"putIv":0.0,"putOi":2},{"callOption":"2026-07-17_60.00_Call","callPrice":0.02,"callDelta":0.1,"callVolume":4,"callIv":129.97,"callOi":370,"putOption":"2026-07-17_60.00_Put","putPrice":16.3,"putDelta":-0.96,"putVolume":0,"putIv":99.75,"putOi":0},{"callOption":"2026-07-17_62.50_Call","callPrice":0.04,"callDelta":0.16,"callVolume":8,"callIv":171.52,"callOi":236,"putOption":"2026-07-17_62.50_Put","putPrice":18.16,"putDelta":-0.96,"putVolume":0,"putIv":108.39,"putOi":0},{"callOption":"2026-07-17_65.00_Call","callPrice":0.06,"callDelta":0.0,"callVolume":0,"callIv":131.05,"callOi":448,"putOption":"2026-07-17_65.00_Put","putPrice":14.7,"putDelta":-0.96,"putVolume":0,"putIv":116.57,"putOi":0},{"callOption":"2026-07-17_67.50_Call","callPrice":0.14,"callDelta":0.0,"callVolume":0,"callIv":116.8,"callOi":366,"putOption":"2026-07-17_67.50_Put","putPrice":17.29,"putDelta":-0.96,"putVolume":0,"putIv":124.35,"putOi":0},{"callOption":"2026-07-17_70.00_Call","callPrice":0.1,"callDelta":0.0,"callVolume":0,"callIv":200.51,"callOi":66,"putOption":"2026-07-17_70.00_Put","putPrice":27.6,"putDelta":-0.96,"putVolume":5,"putIv":131.77,"putOi":107},{"callOption":"2026-07-17_72.50_Call","callPrice":0.45,"callDelta":0.0,"callVolume":0,"callIv":209.16,"callOi":10,"putOption":"2026-07-17_72.50_Put","putPrice":21.19,"putDelta":-0.97,"putVolume":0,"putIv":138.86,"putOi":0},{"callOption":"2026-07-17_75.00_Call","callPrice":0.16,"callDelta":0.0,"callVolume":0,"callIv":145.26,"callOi":42,"putOption":"2026-07-17_75.00_Put","putPrice":13.12,"putDelta":-1.0,"putVolume":0,"putIv":0.0,"putOi":3},{"callOption":"2026-07-17_77.50_Call","callPrice":0.11,"callDelta":0.0,"callVolume":0,"callIv":223.88,"callOi":11,"putOption":"2026-07-17_77.50_Put","putPrice":36.55,"putDelta":-0.97,"putVolume":0,"putIv":152.18,"putOi":0},{"callOption":"2026-07-17_80.00_Call","callPrice":0.35,"callDelta":0.0,"callVolume":0,"callIv":231.36,"callOi":32,"putOption":"2026-07-17_80.00_Put","putPrice":8.5,"putDelta":-0.97,"putVolume":0,"putIv":158.46,"putOi":0},{"callOption":"2026-07-17_85.00_Call","callPrice":0.95,"callDelta":0.0,"callVolume":0,"callIv":208.25,"callOi":74,"putOption":"2026-07-17_85.00_Put","putPrice":44.05,"putDelta":-0.97,"putVolume":0,"putIv":170.34,"putOi":0},{"callOption":"2026-07-17_90.00_Call","callPrice":0.05,"callDelta":0.0,"callVolume":0,"callIv":258.34,"callOi":22,"putOption":"2026-07-17_90.00_Put","putPrice":49.05,"putDelta":-0.97,"putVolume":0,"putIv":181.42,"putOi":0},{"callOption":"2026-07-17_95.00_Call","callPrice":0.4,"callDelta":0.0,"callVolume":0,"callIv":151.47,"callOi":1261,"putOption":"2026-07-17_95.00_Put","putPrice":53.8,"putDelta":0.0,"putVolume":0,"putIv":0.0,"putOi":0},{"callOption":"2026-07-17_100.00_Call","callPrice":1.45,"callDelta":0.0,"callVolume":0,"callIv":283.1,"callOi":6,"putOption":"2026-07-17_100.00_Put","putPrice":58.7,"putDelta":0.0,"putVolume":0,"putIv":0.0,"putOi":0},{"callOption":"2026-07-17_105.00_Call","callPrice":1.05,"callDelta":0.11,"callVolume":0,"callIv":292.1,"callOi":0,"putOption":"2026-07-17_105.00_Put","putPrice":63.7,"putDelta":0.0,"putVolume":0,"putIv":0.0,"putOi":0},{"callOption":"2026-07-17_45.00_Call","callPrice":0.43,"callDelta":0.2,"callVolume":288,"callIv":48.95,"callOi":2987,"putOption":"2026-07-17_45.00_Put","putPrice":4.9,"putDelta":-0.82,"putVolume":3,"putIv":46.04,"putOi":1129},{"callOption":"2026-07-17_47.50_Call","callPrice":0.2,"callDelta":0.09,"callVolume":34,"callIv":50.08,"callOi":4799,"putOption":"2026-07-17_47.50_Put","putPrice":9.92,"putDelta":-0.91,"putVolume":0,"putIv":69.44,"putOi":324},{"callOption":"2026-07-17_82.50_Call","callPrice":1.2,"callDelta":0.0,"callVolume":0,"callIv":216.89,"callOi":7,"putOption":"2026-07-17_82.50_Put","putPrice":41.55,"putDelta":-0.97,"putVolume":0,"putIv":164.51,"putOi":0},{"callOption":"2026-07-17_110.00_Call","callPrice":1.05,"callDelta":0.11,"callVolume":0,"callIv":301.98,"callOi":0,"putOption":"2026-07-17_110.00_Put","putPrice":69.05,"putDelta":-0.97,"putVolume":0,"putIv":219.64,"putOi":0},{"callOption":"2026-07-17_87.50_Call","callPrice":0.75,"callDelta":0.0,"callVolume":0,"callIv":251.99,"callOi":5,"putOption":"2026-07-17_87.50_Put","putPrice":46.55,"putDelta":-0.97,"putVolume":0,"putIv":175.97,"putOi":0},{"callOption":"2026-07-17_115.00_Call","callPrice":0.68,"callDelta":0.08,"callVolume":0,"callIv":284.49,"callOi":0,"putOption":"2026-07-17_115.00_Put","putPrice":74.0,"putDelta":-0.98,"putVolume":0,"putIv":216.49,"putOi":0},{"callOption":"2026-07-17_92.50_Call","callPrice":3.8,"callDelta":0.0,"callVolume":0,"callIv":264.46,"callOi":3,"putOption":"2026-07-17_92.50_Put","putPrice":51.65,"putDelta":-0.96,"putVolume":0,"putIv":201.91,"putOi":0},{"callOption":"2026-07-17_120.00_Call","callPrice":0.68,"callDelta":0.07,"callVolume":0,"callIv":292.92,"callOi":0,"putOption":"2026-07-17_120.00_Put","putPrice":79.0,"putDelta":-0.98,"putVolume":0,"putIv":224.28,"putOi":0},{"callOption":"2026-08-21_25.00_Call","callPrice":16.35,"callDelta":0.95,"callVolume":0,"callIv":88.76,"callOi":0,"putOption":"2026-08-21_25.00_Put","putPrice":0.22,"putDelta":-0.04,"putVolume":1,"putIv":80.86,"putOi":11},{"callOption":"2026-08-21_70.00_Call","callPrice":0.13,"callDelta":0.02,"callVolume":0,"callIv":95.96,"callOi":1,"putOption":"2026-08-21_70.00_Put","putPrice":28.9,"putDelta":0.0,"putVolume":0,"putIv":0.0,"putOi":0},{"callOption":"2026-08-21_65.00_Call","callPrice":1.1,"callDelta":0.16,"callVolume":0,"callIv":102.48,"callOi":0,"putOption":"2026-08-21_65.00_Put","putPrice":23.85,"putDelta":0.0,"putVolume":0,"putIv":0.0,"putOi":0},{"callOption":"2026-08-21_60.00_Call","callPrice":0.38,"callDelta":0.08,"callVolume":0,"callIv":62.23,"callOi":3,"putOption":"2026-08-21_60.00_Put","putPrice":18.9,"putDelta":0.0,"putVolume":0,"putIv":0.0,"putOi":0},{"callOption":"2026-08-21_57.50_Call","callPrice":0.35,"callDelta":0.11,"callVolume":0,"callIv":85.27,"callOi":9,"putOption":"2026-08-21_57.50_Put","putPrice":16.5,"putDelta":-0.96,"putVolume":0,"putIv":49.7,"putOi":0},{"callOption":"2026-08-21_55.00_Call","callPrice":0.57,"callDelta":0.14,"callVolume":0,"callIv":53.3,"callOi":14,"putOption":"2026-08-21_55.00_Put","putPrice":13.1,"putDelta":-0.86,"putVolume":0,"putIv":50.17,"putOi":6},{"callOption":"2026-08-21_52.50_Call","callPrice":0.56,"callDelta":0.12,"callVolume":11,"callIv":51.37,"callOi":28,"putOption":"2026-08-21_52.50_Put","putPrice":11.85,"putDelta":-0.87,"putVolume":0,"putIv":53.15,"putOi":0},{"callOption":"2026-08-21_50.00_Call","callPrice":0.85,"callDelta":0.15,"callVolume":30,"callIv":46.27,"callOi":85,"putOption":"2026-08-21_50.00_Put","putPrice":12.1,"putDelta":-0.85,"putVolume":0,"putIv":52.23,"putOi":7},{"callOption":"2026-08-21_47.50_Call","callPrice":1.18,"callDelta":0.27,"callVolume":60,"callIv":54.91,"callOi":97,"putOption":"2026-08-21_47.50_Put","putPrice":8.44,"putDelta":-0.73,"putVolume":0,"putIv":51.83,"putOi":5},{"callOption":"2026-08-21_45.00_Call","callPrice":1.95,"callDelta":0.36,"callVolume":208,"callIv":54.1,"callOi":110,"putOption":"2026-08-21_45.00_Put","putPrice":5.7,"putDelta":-0.66,"putVolume":6,"putIv":48.16,"putOi":8},{"callOption":"2026-08-21_42.50_Call","callPrice":2.65,"callDelta":0.48,"callVolume":36,"callIv":57.39,"callOi":658,"putOption":"2026-08-21_42.50_Put","putPrice":4.2,"putDelta":-0.53,"putVolume":21,"putIv":51.7,"putOi":4},{"callOption":"2026-08-21_40.00_Call","callPrice":3.87,"callDelta":0.59,"callVolume":24,"callIv":66.27,"callOi":109,"putOption":"2026-08-21_40.00_Put","putPrice":2.8,"putDelta":-0.41,"putVolume":39,"putIv":56.06,"putOi":236},{"callOption":"2026-08-21_37.50_Call","callPrice":5.2,"callDelta":0.7,"callVolume":15,"callIv":59.6,"callOi":67,"putOption":"2026-08-21_37.50_Put","putPrice":1.63,"putDelta":-0.29,"putVolume":98,"putIv":53.6,"putOi":75},{"callOption":"2026-08-21_35.00_Call","callPrice":7.88,"callDelta":0.79,"callVolume":0,"callIv":58.93,"callOi":5,"putOption":"2026-08-21_35.00_Put","putPrice":0.87,"putDelta":-0.16,"putVolume":47,"putIv":48.41,"putOi":108},{"callOption":"2026-08-21_32.50_Call","callPrice":9.82,"callDelta":0.87,"callVolume":0,"callIv":77.49,"callOi":1,"putOption":"2026-08-21_32.50_Put","putPrice":0.6,"putDelta":-0.12,"putVolume":72,"putIv":57.74,"putOi":99},{"callOption":"2026-08-21_30.00_Call","callPrice":11.9,"callDelta":0.91,"callVolume":36,"callIv":69.49,"callOi":31,"putOption":"2026-08-21_30.00_Put","putPrice":0.32,"putDelta":-0.09,"putVolume":22,"putIv":68.71,"putOi":12},{"callOption":"2026-08-21_27.50_Call","callPrice":13.9,"callDelta":0.94,"callVolume":0,"callIv":76.89,"callOi":0,"putOption":"2026-08-21_27.50_Put","putPrice":0.3,"putDelta":-0.06,"putVolume":0,"putIv":72.52,"putOi":1},{"callOption":"2026-09-18_25.00_Call","callPrice":16.5,"callDelta":0.93,"callVolume":0,"callIv":79.22,"callOi":0,"putOption":"2026-09-18_25.00_Put","putPrice":0.58,"putDelta":-0.07,"putVolume":0,"putIv":83.34,"putOi":0},{"callOption":"2026-09-18_27.50_Call","callPrice":13.8,"callDelta":0.95,"callVolume":0,"callIv":57.63,"callOi":0,"putOption":"2026-09-18_27.50_Put","putPrice":0.28,"putDelta":-0.05,"putVolume":0,"putIv":89.01,"putOi":3},{"callOption":"2026-09-18_40.00_Call","callPrice":4.4,"callDelta":0.59,"callVolume":146,"callIv":53.94,"callOi":11,"putOption":"2026-09-18_40.00_Put","putPrice":3.5,"putDelta":-0.41,"putVolume":200,"putIv":52.67,"putOi":807},{"callOption":"2026-09-18_42.50_Call","callPrice":3.3,"callDelta":0.49,"callVolume":253,"callIv":52.7,"callOi":1,"putOption":"2026-09-18_42.50_Put","putPrice":5.0,"putDelta":-0.51,"putVolume":6,"putIv":51.66,"putOi":23},{"callOption":"2026-09-18_45.00_Call","callPrice":2.4,"callDelta":0.4,"callVolume":196,"callIv":51.39,"callOi":289,"putOption":"2026-09-18_45.00_Put","putPrice":6.4,"putDelta":-0.6,"putVolume":141,"putIv":50.86,"putOi":62},{"callOption":"2026-09-18_47.50_Call","callPrice":1.7,"callDelta":0.31,"callVolume":2,"callIv":51.36,"callOi":8,"putOption":"2026-09-18_47.50_Put","putPrice":8.45,"putDelta":-0.69,"putVolume":0,"putIv":50.59,"putOi":74},{"callOption":"2026-09-18_50.00_Call","callPrice":0.55,"callDelta":0.32,"callVolume":0,"callIv":51.43,"callOi":238,"putOption":"2026-09-18_50.00_Put","putPrice":13.0,"putDelta":-0.68,"putVolume":0,"putIv":52.43,"putOi":463},{"callOption":"2026-09-18_55.00_Call","callPrice":0.5,"callDelta":0.14,"callVolume":2,"callIv":52.37,"callOi":207,"putOption":"2026-09-18_55.00_Put","putPrice":18.0,"putDelta":-0.86,"putVolume":0,"putIv":50.49,"putOi":270},{"callOption":"2026-09-18_60.00_Call","callPrice":0.35,"callDelta":0.19,"callVolume":1,"callIv":76.8,"callOi":269,"putOption":"2026-09-18_60.00_Put","putPrice":19.9,"putDelta":-0.81,"putVolume":0,"putIv":0.0,"putOi":345},{"callOption":"2026-09-18_65.00_Call","callPrice":0.3,"callDelta":0.09,"callVolume":0,"callIv":64.61,"callOi":790,"putOption":"2026-09-18_65.00_Put","putPrice":24.9,"putDelta":-0.91,"putVolume":0,"putIv":59.53,"putOi":146},{"callOption":"2026-09-18_70.00_Call","callPrice":0.15,"callDelta":0.06,"callVolume":0,"callIv":67.18,"callOi":335,"putOption":"2026-09-18_70.00_Put","putPrice":28.7,"putDelta":-0.88,"putVolume":4,"putIv":83.1,"putOi":60},{"callOption":"2026-09-18_72.50_Call","callPrice":0.2,"callDelta":0.04,"callVolume":0,"callIv":77.38,"callOi":282,"putOption":"2026-09-18_72.50_Put","putPrice":31.35,"putDelta":-0.96,"putVolume":0,"putIv":0.0,"putOi":11},{"callOption":"2026-09-18_75.00_Call","callPrice":0.28,"callDelta":0.03,"callVolume":0,"callIv":80.74,"callOi":131,"putOption":"2026-09-18_75.00_Put","putPrice":22.72,"putDelta":-0.97,"putVolume":0,"putIv":0.0,"putOi":4},{"callOption":"2026-09-18_77.50_Call","callPrice":0.54,"callDelta":0.03,"callVolume":0,"callIv":96.29,"callOi":136,"putOption":"2026-09-18_77.50_Put","putPrice":36.35,"putDelta":0.0,"putVolume":0,"putIv":0.0,"putOi":0},{"callOption":"2026-09-18_80.00_Call","callPrice":0.32,"callDelta":0.02,"callVolume":0,"callIv":102.88,"callOi":247,"putOption":"2026-09-18_80.00_Put","putPrice":38.85,"putDelta":0.0,"putVolume":0,"putIv":0.0,"putOi":0},{"callOption":"2026-09-18_82.50_Call","callPrice":0.1,"callDelta":0.02,"callVolume":0,"callIv":108.63,"callOi":8,"putOption":"2026-09-18_82.50_Put","putPrice":31.2,"putDelta":0.0,"putVolume":0,"putIv":0.0,"putOi":0},{"callOption":"2026-09-18_85.00_Call","callPrice":0.14,"callDelta":0.01,"callVolume":0,"callIv":111.74,"callOi":114,"putOption":"2026-09-18_85.00_Put","putPrice":43.8,"putDelta":0.0,"putVolume":0,"putIv":0.0,"putOi":0},{"callOption":"2026-09-18_87.50_Call","callPrice":0.29,"callDelta":0.01,"callVolume":0,"callIv":114.09,"callOi":7,"putOption":"2026-09-18_87.50_Put","putPrice":46.3,"putDelta":0.0,"putVolume":0,"putIv":0.0,"putOi":0},{"callOption":"2026-09-18_90.00_Call","callPrice":0.14,"callDelta":0.01,"callVolume":0,"callIv":80.68,"callOi":243,"putOption":"2026-09-18_90.00_Put","putPrice":48.8,"putDelta":0.0,"putVolume":0,"putIv":0.0,"putOi":0},{"callOption":"2026-09-18_95.00_Call","callPrice":0.58,"callDelta":0.0,"callVolume":0,"callIv":122.39,"callOi":65,"putOption":"2026-09-18_95.00_Put","putPrice":53.85,"putDelta":0.0,"putVolume":0,"putIv":0.0,"putOi":0},{"callOption":"2026-09-18_100.00_Call","callPrice":1.85,"callDelta":0.0,"callVolume":0,"callIv":127.46,"callOi":1,"putOption":"2026-09-18_100.00_Put","putPrice":58.8,"putDelta":0.0,"putVolume":0,"putIv":0.0,"putOi":0},{"callOption":"2026-09-18_105.00_Call","callPrice":0.55,"callDelta":0.0,"callVolume":0,"callIv":132.2,"callOi":11,"putOption":"2026-09-18_105.00_Put","putPrice":63.85,"putDelta":0.0,"putVolume":0,"putIv":0.0,"putOi":0},{"callOption":"2026-09-18_110.00_Call","callPrice":0.98,"callDelta":0.0,"callVolume":0,"callIv":133.78,"callOi":2,"putOption":"2026-09-18_110.00_Put","putPrice":68.85,"putDelta":0.0,"putVolume":0,"putIv":0.0,"putOi":0},{"callOption":"2026-09-18_115.00_Call","callPrice":0.07,"callDelta":0.0,"callVolume":0,"callIv":140.88,"callOi":6,"putOption":"2026-09-18_115.00_Put","putPrice":73.85,"putDelta":0.0,"putVolume":0,"putIv":0.0,"putOi":0},{"callOption":"2026-09-18_120.00_Call","callPrice":0.07,"callDelta":0.0,"callVolume":0,"callIv":144.86,"callOi":2,"putOption":"2026-09-18_120.00_Put","putPrice":78.85,"putDelta":0.0,"putVolume":0,"putIv":0.0,"putOi":0},{"callOption":"2026-09-18_30.00_Call","callPrice":12.05,"callDelta":0.89,"callVolume":0,"callIv":48.94,"callOi":1,"putOption":"2026-09-18_30.00_Put","putPrice":0.6,"putDelta":-0.11,"putVolume":2,"putIv":61.41,"putOi":44},{"callOption":"2026-09-18_67.50_Call","callPrice":0.13,"callDelta":0.03,"callVolume":1,"callIv":52.52,"callOi":164,"putOption":"2026-09-18_67.50_Put","putPrice":14.91,"putDelta":-0.97,"putVolume":0,"putIv":0.0,"putOi":11},{"callOption":"2026-09-18_37.50_Call","callPrice":4.0,"callDelta":0.68,"callVolume":0,"callIv":49.42,"callOi":4,"putOption":"2026-09-18_37.50_Put","putPrice":2.37,"putDelta":-0.31,"putVolume":13,"putIv":53.41,"putOi":45},{"callOption":"2026-09-18_62.50_Call","callPrice":0.35,"callDelta":0.07,"callVolume":176,"callIv":57.04,"callOi":475,"putOption":"2026-09-18_62.50_Put","putPrice":21.5,"putDelta":-0.93,"putVolume":0,"putIv":57.48,"putOi":246},{"callOption":"2026-09-18_35.00_Call","callPrice":8.44,"callDelta":0.76,"callVolume":0,"callIv":59.02,"callOi":5,"putOption":"2026-09-18_35.00_Put","putPrice":1.55,"putDelta":-0.21,"putVolume":4,"putIv":51.57,"putOi":279},{"callOption":"2026-09-18_57.50_Call","callPrice":0.26,"callDelta":0.17,"callVolume":0,"callIv":74.17,"callOi":160,"putOption":"2026-09-18_57.50_Put","putPrice":18.7,"putDelta":-0.83,"putVolume":0,"putIv":57.23,"putOi":184},{"callOption":"2026-09-18_52.50_Call","callPrice":1.01,"callDelta":0.26,"callVolume":0,"callIv":51.85,"callOi":239,"putOption":"2026-09-18_52.50_Put","putPrice":12.75,"putDelta":-0.85,"putVolume":5,"putIv":45.84,"putOi":478},{"callOption":"2026-09-18_32.50_Call","callPrice":9.25,"callDelta":0.87,"callVolume":0,"callIv":50.06,"callOi":0,"putOption":"2026-09-18_32.50_Put","putPrice":1.55,"putDelta":-0.13,"putVolume":0,"putIv":53.93,"putOi":20},{"callOption":"2026-09-18_92.50_Call","callPrice":0.15,"callDelta":0.01,"callVolume":0,"callIv":117.71,"callOi":3,"putOption":"2026-09-18_92.50_Put","putPrice":51.3,"putDelta":0.0,"putVolume":0,"putIv":0.0,"putOi":0},{"callOption":"2026-09-18_125.00_Call","callPrice":0.38,"callDelta":0.05,"callVolume":0,"callIv":122.21,"callOi":0,"putOption":"2026-09-18_125.00_Put","putPrice":83.85,"putDelta":0.0,"putVolume":0,"putIv":0.0,"putOi":0},{"callOption":"2026-10-16_25.00_Call","callPrice":16.55,"callDelta":0.93,"callVolume":0,"callIv":70.53,"callOi":0,"putOption":"2026-10-16_25.00_Put","putPrice":0.22,"putDelta":-0.07,"putVolume":0,"putIv":89.64,"putOi":2},{"callOption":"2026-10-16_27.50_Call","callPrice":14.15,"callDelta":0.91,"callVolume":0,"callIv":62.11,"callOi":0,"putOption":"2026-10-16_27.50_Put","putPrice":0.8,"putDelta":-0.09,"putVolume":0,"putIv":62.06,"putOi":10},{"callOption":"2026-10-16_30.00_Call","callPrice":12.15,"callDelta":0.86,"callVolume":0,"callIv":62.67,"callOi":0,"putOption":"2026-10-16_30.00_Put","putPrice":0.55,"putDelta":-0.14,"putVolume":0,"putIv":56.98,"putOi":25},{"callOption":"2026-10-16_52.50_Call","callPrice":1.25,"callDelta":0.23,"callVolume":1,"callIv":50.9,"callOi":461,"putOption":"2026-10-16_52.50_Put","putPrice":9.5,"putDelta":-0.77,"putVolume":0,"putIv":48.58,"putOi":377},{"callOption":"2026-10-16_32.50_Call","callPrice":10.05,"callDelta":0.81,"callVolume":0,"callIv":58.22,"callOi":0,"putOption":"2026-10-16_32.50_Put","putPrice":1.6,"putDelta":-0.19,"putVolume":0,"putIv":52.13,"putOi":9},{"callOption":"2026-10-16_40.00_Call","callPrice":4.79,"callDelta":0.59,"callVolume":141,"callIv":55.74,"callOi":213,"putOption":"2026-10-16_40.00_Put","putPrice":5.3,"putDelta":-0.41,"putVolume":0,"putIv":50.07,"putOi":8110},{"callOption":"2026-10-16_37.50_Call","callPrice":6.05,"callDelta":0.68,"callVolume":0,"callIv":47.68,"callOi":0,"putOption":"2026-10-16_37.50_Put","putPrice":3.8,"putDelta":-0.32,"putVolume":0,"putIv":51.11,"putOi":53},{"callOption":"2026-10-16_35.00_Call","callPrice":8.1,"callDelta":0.75,"callVolume":0,"callIv":54.48,"callOi":0,"putOption":"2026-10-16_35.00_Put","putPrice":3.0,"putDelta":-0.25,"putVolume":0,"putIv":51.19,"putOi":51},{"callOption":"2026-10-16_100.00_Call","callPrice":1.08,"callDelta":0.11,"callVolume":0,"callIv":109.55,"callOi":0,"putOption":"2026-10-16_100.00_Put","putPrice":58.85,"putDelta":0.0,"putVolume":0,"putIv":0.0,"putOi":0},{"callOption":"2026-10-16_95.00_Call","callPrice":1.08,"callDelta":0.12,"callVolume":0,"callIv":105.19,"callOi":0,"putOption":"2026-10-16_95.00_Put","putPrice":53.85,"putDelta":0.0,"putVolume":0,"putIv":0.0,"putOi":0},{"callOption":"2026-10-16_90.00_Call","callPrice":0.23,"callDelta":0.02,"callVolume":0,"callIv":101.08,"callOi":40,"putOption":"2026-10-16_90.00_Put","putPrice":48.85,"putDelta":0.0,"putVolume":0,"putIv":0.0,"putOi":0},{"callOption":"2026-10-16_85.00_Call","callPrice":0.86,"callDelta":0.03,"callVolume":0,"callIv":85.05,"callOi":1,"putOption":"2026-10-16_85.00_Put","putPrice":43.85,"putDelta":0.0,"putVolume":0,"putIv":0.0,"putOi":0},{"callOption":"2026-10-16_80.00_Call","callPrice":0.1,"callDelta":0.04,"callVolume":0,"callIv":90.58,"callOi":20,"putOption":"2026-10-16_80.00_Put","putPrice":38.85,"putDelta":0.0,"putVolume":0,"putIv":0.0,"putOi":0},{"callOption":"2026-10-16_75.00_Call","callPrice":0.2,"callDelta":0.07,"callVolume":0,"callIv":85.63,"callOi":22,"putOption":"2026-10-16_75.00_Put","putPrice":33.85,"putDelta":0.0,"putVolume":0,"putIv":0.0,"putOi":0},{"callOption":"2026-10-16_72.50_Call","callPrice":0.15,"callDelta":0.08,"callVolume":0,"callIv":69.35,"callOi":38,"putOption":"2026-10-16_72.50_Put","putPrice":31.45,"putDelta":-0.98,"putVolume":0,"putIv":53.34,"putOi":0},{"callOption":"2026-10-16_70.00_Call","callPrice":0.25,"callDelta":0.09,"callVolume":0,"callIv":76.05,"callOi":30,"putOption":"2026-10-16_70.00_Put","putPrice":10.43,"putDelta":-0.98,"putVolume":0,"putIv":50.31,"putOi":0},{"callOption":"2026-10-16_67.50_Call","callPrice":0.45,"callDelta":0.11,"callVolume":0,"callIv":63.0,"callOi":131,"putOption":"2026-10-16_67.50_Put","putPrice":16.0,"putDelta":-0.89,"putVolume":0,"putIv":47.15,"putOi":10},{"callOption":"2026-10-16_65.00_Call","callPrice":0.35,"callDelta":0.13,"callVolume":0,"callIv":68.86,"callOi":142,"putOption":"2026-10-16_65.00_Put","putPrice":20.18,"putDelta":-0.87,"putVolume":0,"putIv":43.86,"putOi":20},{"callOption":"2026-10-16_62.50_Call","callPrice":0.45,"callDelta":0.16,"callVolume":0,"callIv":65.87,"callOi":137,"putOption":"2026-10-16_62.50_Put","putPrice":6.68,"putDelta":-0.84,"putVolume":0,"putIv":51.98,"putOi":2},{"callOption":"2026-10-16_60.00_Call","callPrice":0.5,"callDelta":0.19,"callVolume":0,"callIv":50.23,"callOi":715,"putOption":"2026-10-16_60.00_Put","putPrice":18.5,"putDelta":-0.81,"putVolume":0,"putIv":49.4,"putOi":96},{"callOption":"2026-10-16_57.50_Call","callPrice":0.65,"callDelta":0.23,"callVolume":0,"callIv":50.57,"callOi":681,"putOption":"2026-10-16_57.50_Put","putPrice":9.1,"putDelta":-0.77,"putVolume":0,"putIv":46.37,"putOi":94},{"callOption":"2026-10-16_55.00_Call","callPrice":0.9,"callDelta":0.2,"callVolume":10,"callIv":53.95,"callOi":1259,"putOption":"2026-10-16_55.00_Put","putPrice":15.5,"putDelta":-0.77,"putVolume":25,"putIv":58.91,"putOi":427},{"callOption":"2026-10-16_50.00_Call","callPrice":1.75,"callDelta":0.28,"callVolume":2,"callIv":51.46,"callOi":90,"putOption":"2026-10-16_50.00_Put","putPrice":8.35,"putDelta":-0.72,"putVolume":0,"putIv":46.83,"putOi":166},{"callOption":"2026-10-16_47.50_Call","callPrice":2.3,"callDelta":0.35,"callVolume":1,"callIv":50.69,"callOi":10,"putOption":"2026-10-16_47.50_Put","putPrice":4.0,"putDelta":-0.65,"putVolume":0,"putIv":51.87,"putOi":114},{"callOption":"2026-10-16_45.00_Call","callPrice":3.1,"callDelta":0.42,"callVolume":6,"callIv":51.16,"callOi":41,"putOption":"2026-10-16_45.00_Put","putPrice":7.98,"putDelta":-0.58,"putVolume":0,"putIv":53.8,"putOi":732},{"callOption":"2026-10-16_42.50_Call","callPrice":3.92,"callDelta":0.5,"callVolume":6,"callIv":51.56,"callOi":62,"putOption":"2026-10-16_42.50_Put","putPrice":5.4,"putDelta":-0.5,"putVolume":0,"putIv":49.11,"putOi":48},{"callOption":"2026-12-18_22.50_Call","callPrice":19.15,"callDelta":0.93,"callVolume":0,"callIv":69.98,"callOi":0,"putOption":"2026-12-18_22.50_Put","putPrice":0.49,"putDelta":-0.07,"putVolume":0,"putIv":81.33,"putOi":2},{"callOption":"2026-12-18_25.00_Call","callPrice":17.0,"callDelta":0.9,"callVolume":0,"callIv":67.59,"callOi":0,"putOption":"2026-12-18_25.00_Put","putPrice":1.05,"putDelta":-0.1,"putVolume":0,"putIv":67.49,"putOi":23},{"callOption":"2026-12-18_27.50_Call","callPrice":15.1,"callDelta":0.88,"callVolume":0,"callIv":59.96,"callOi":2,"putOption":"2026-12-18_27.50_Put","putPrice":1.5,"putDelta":-0.12,"putVolume":0,"putIv":59.4,"putOi":71},{"callOption":"2026-12-18_30.00_Call","callPrice":12.3,"callDelta":0.84,"callVolume":1,"callIv":54.03,"callOi":3,"putOption":"2026-12-18_30.00_Put","putPrice":1.7,"putDelta":-0.16,"putVolume":1,"putIv":56.99,"putOi":28},{"callOption":"2026-12-18_52.50_Call","callPrice":1.45,"callDelta":0.38,"callVolume":0,"callIv":51.25,"callOi":111,"putOption":"2026-12-18_52.50_Put","putPrice":7.4,"putDelta":-0.62,"putVolume":0,"putIv":51.04,"putOi":147},{"callOption":"2026-12-18_57.50_Call","callPrice":1.13,"callDelta":0.31,"callVolume":0,"callIv":51.05,"callOi":60,"putOption":"2026-12-18_57.50_Put","putPrice":18.7,"putDelta":-0.69,"putVolume":0,"putIv":47.37,"putOi":7},{"callOption":"2026-12-18_32.50_Call","callPrice":10.4,"callDelta":0.79,"callVolume":1,"callIv":54.19,"callOi":9,"putOption":"2026-12-18_32.50_Put","putPrice":2.25,"putDelta":-0.21,"putVolume":14,"putIv":55.73,"putOi":58},{"callOption":"2026-12-18_35.00_Call","callPrice":8.2,"callDelta":0.73,"callVolume":1,"callIv":52.81,"callOi":5,"putOption":"2026-12-18_35.00_Put","putPrice":3.0,"putDelta":-0.26,"putVolume":3,"putIv":54.21,"putOi":457},{"callOption":"2026-12-18_37.50_Call","callPrice":7.7,"callDelta":0.66,"callVolume":0,"callIv":54.32,"callOi":0,"putOption":"2026-12-18_37.50_Put","putPrice":3.9,"putDelta":-0.33,"putVolume":13,"putIv":53.42,"putOi":204},{"callOption":"2026-12-18_40.00_Call","callPrice":5.1,"callDelta":0.62,"callVolume":0,"callIv":59.57,"callOi":31,"putOption":"2026-12-18_40.00_Put","putPrice":5.0,"putDelta":-0.39,"putVolume":89,"putIv":51.54,"putOi":362},{"callOption":"2026-12-18_42.50_Call","callPrice":5.3,"callDelta":0.53,"callVolume":11,"callIv":53.03,"callOi":612,"putOption":"2026-12-18_42.50_Put","putPrice":6.6,"putDelta":-0.46,"putVolume":153,"putIv":51.42,"putOi":275},{"callOption":"2026-12-18_45.00_Call","callPrice":4.3,"callDelta":0.47,"callVolume":174,"callIv":52.09,"callOi":629,"putOption":"2026-12-18_45.00_Put","putPrice":7.8,"putDelta":-0.54,"putVolume":39,"putIv":48.03,"putOi":263},{"callOption":"2026-12-18_47.50_Call","callPrice":3.5,"callDelta":0.4,"callVolume":168,"callIv":51.69,"callOi":459,"putOption":"2026-12-18_47.50_Put","putPrice":9.6,"putDelta":-0.58,"putVolume":28,"putIv":52.9,"putOi":195},{"callOption":"2026-12-18_50.00_Call","callPrice":2.55,"callDelta":0.35,"callVolume":2,"callIv":51.52,"callOi":265,"putOption":"2026-12-18_50.00_Put","putPrice":12.6,"putDelta":-0.65,"putVolume":0,"putIv":48.14,"putOi":242},{"callOption":"2026-12-18_55.00_Call","callPrice":1.9,"callDelta":0.26,"callVolume":5,"callIv":51.87,"callOi":19,"putOption":"2026-12-18_55.00_Put","putPrice":17.65,"putDelta":-0.74,"putVolume":0,"putIv":49.89,"putOi":246},{"callOption":"2026-12-18_60.00_Call","callPrice":1.29,"callDelta":0.18,"callVolume":15,"callIv":51.56,"callOi":29,"putOption":"2026-12-18_60.00_Put","putPrice":11.8,"putDelta":-0.82,"putVolume":0,"putIv":49.89,"putOi":44},{"callOption":"2026-12-18_62.50_Call","callPrice":1.25,"callDelta":0.24,"callVolume":0,"callIv":47.8,"callOi":511,"putOption":"2026-12-18_62.50_Put","putPrice":15.0,"putDelta":-0.76,"putVolume":0,"putIv":44.97,"putOi":30},{"callOption":"2026-12-18_65.00_Call","callPrice":0.72,"callDelta":0.22,"callVolume":0,"callIv":46.09,"callOi":32,"putOption":"2026-12-18_65.00_Put","putPrice":22.25,"putDelta":-0.78,"putVolume":0,"putIv":47.1,"putOi":16},{"callOption":"2026-12-18_67.50_Call","callPrice":0.55,"callDelta":0.19,"callVolume":0,"callIv":58.19,"callOi":517,"putOption":"2026-12-18_67.50_Put","putPrice":26.7,"putDelta":-0.81,"putVolume":0,"putIv":48.97,"putOi":21},{"callOption":"2026-12-18_70.00_Call","callPrice":0.73,"callDelta":0.17,"callVolume":0,"callIv":52.41,"callOi":59,"putOption":"2026-12-18_70.00_Put","putPrice":4.89,"putDelta":-0.83,"putVolume":0,"putIv":45.33,"putOi":24},{"callOption":"2026-12-18_72.50_Call","callPrice":1.65,"callDelta":0.15,"callVolume":0,"callIv":50.73,"callOi":6,"putOption":"2026-12-18_72.50_Put","putPrice":4.6,"putDelta":-0.85,"putVolume":0,"putIv":44.9,"putOi":12},{"callOption":"2026-12-18_75.00_Call","callPrice":0.55,"callDelta":0.13,"callVolume":0,"callIv":57.2,"callOi":228,"putOption":"2026-12-18_75.00_Put","putPrice":31.65,"putDelta":-0.87,"putVolume":0,"putIv":0.0,"putOi":11},{"callOption":"2026-12-18_77.50_Call","callPrice":1.31,"callDelta":0.12,"callVolume":0,"callIv":52.93,"callOi":3,"putOption":"2026-12-18_77.50_Put","putPrice":38.35,"putDelta":0.0,"putVolume":0,"putIv":0.0,"putOi":0},{"callOption":"2026-12-18_80.00_Call","callPrice":0.5,"callDelta":0.11,"callVolume":0,"callIv":57.84,"callOi":47,"putOption":"2026-12-18_80.00_Put","putPrice":38.8,"putDelta":0.0,"putVolume":0,"putIv":0.0,"putOi":0},{"callOption":"2026-12-18_85.00_Call","callPrice":0.15,"callDelta":0.08,"callVolume":0,"callIv":57.85,"callOi":5163,"putOption":"2026-12-18_85.00_Put","putPrice":25.05,"putDelta":0.0,"putVolume":0,"putIv":0.0,"putOi":0},{"callOption":"2026-12-18_90.00_Call","callPrice":0.84,"callDelta":0.06,"callVolume":0,"callIv":60.39,"callOi":13,"putOption":"2026-12-18_90.00_Put","putPrice":48.85,"putDelta":0.0,"putVolume":0,"putIv":0.0,"putOi":0},{"callOption":"2026-12-18_95.00_Call","callPrice":0.1,"callDelta":0.03,"callVolume":4,"callIv":59.17,"callOi":9,"putOption":"2026-12-18_95.00_Put","putPrice":53.85,"putDelta":0.0,"putVolume":0,"putIv":0.0,"putOi":0},{"callOption":"2026-12-18_100.00_Call","callPrice":0.1,"callDelta":0.04,"callVolume":0,"callIv":57.33,"callOi":5,"putOption":"2026-12-18_100.00_Put","putPrice":58.9,"putDelta":0.0,"putVolume":0,"putIv":0.0,"putOi":0},{"callOption":"2026-12-18_105.00_Call","callPrice":2.95,"callDelta":0.03,"callVolume":0,"callIv":90.4,"callOi":1,"putOption":"2026-12-18_105.00_Put","putPrice":63.8,"putDelta":0.0,"putVolume":0,"putIv":0.0,"putOi":0},{"callOption":"2026-12-18_82.50_Call","callPrice":0.2,"callDelta":0.09,"callVolume":0,"callIv":61.79,"callOi":12,"putOption":"2026-12-18_82.50_Put","putPrice":41.3,"putDelta":0.0,"putVolume":0,"putIv":0.0,"putOi":0},{"callOption":"2026-12-18_110.00_Call","callPrice":0.47,"callDelta":0.02,"callVolume":0,"callIv":93.44,"callOi":5,"putOption":"2026-12-18_110.00_Put","putPrice":68.8,"putDelta":0.0,"putVolume":0,"putIv":0.0,"putOi":0},{"callOption":"2026-12-18_87.50_Call","callPrice":0.15,"callDelta":0.07,"callVolume":0,"callIv":58.71,"callOi":8,"putOption":"2026-12-18_87.50_Put","putPrice":46.3,"putDelta":0.0,"putVolume":0,"putIv":0.0,"putOi":0},{"callOption":"2026-12-18_115.00_Call","callPrice":1.08,"callDelta":0.11,"callVolume":0,"callIv":95.83,"callOi":0,"putOption":"2026-12-18_115.00_Put","putPrice":73.8,"putDelta":0.0,"putVolume":0,"putIv":0.0,"putOi":0},{"callOption":"2026-12-18_120.00_Call","callPrice":0.8,"callDelta":0.02,"callVolume":0,"callIv":84.1,"callOi":50,"putOption":"2026-12-18_120.00_Put","putPrice":78.8,"putDelta":0.0,"putVolume":0,"putIv":0.0,"putOi":0},{"callOption":"2026-12-18_92.50_Call","callPrice":1.64,"callDelta":0.06,"callVolume":0,"callIv":54.88,"callOi":5,"putOption":"2026-12-18_92.50_Put","putPrice":51.35,"putDelta":0.0,"putVolume":0,"putIv":0.0,"putOi":0},{"callOption":"2026-12-18_125.00_Call","callPrice":1.08,"callDelta":0.1,"callVolume":0,"callIv":101.11,"callOi":0,"putOption":"2026-12-18_125.00_Put","putPrice":83.8,"putDelta":0.0,"putVolume":0,"putIv":0.0,"putOi":0},{"callOption":"2027-01-15_50.00_Call","callPrice":2.1,"callDelta":0.45,"callVolume":0,"callIv":50.39,"callOi":142,"putOption":"2027-01-15_50.00_Put","putPrice":10.7,"putDelta":-0.55,"putVolume":0,"putIv":47.33,"putOi":369},{"callOption":"2027-01-15_55.00_Call","callPrice":2.35,"callDelta":0.28,"callVolume":3,"callIv":50.82,"callOi":78,"putOption":"2027-01-15_55.00_Put","putPrice":16.3,"putDelta":-0.73,"putVolume":10,"putIv":49.42,"putOi":209},{"callOption":"2027-01-15_60.00_Call","callPrice":1.3,"callDelta":0.3,"callVolume":0,"callIv":50.47,"callOi":974,"putOption":"2027-01-15_60.00_Put","putPrice":20.7,"putDelta":-0.81,"putVolume":37,"putIv":48.29,"putOi":428},{"callOption":"2027-01-15_65.00_Call","callPrice":1.15,"callDelta":0.25,"callVolume":0,"callIv":47.84,"callOi":95,"putOption":"2027-01-15_65.00_Put","putPrice":26.2,"putDelta":-0.75,"putVolume":0,"putIv":47.47,"putOi":826},{"callOption":"2027-01-15_67.50_Call","callPrice":0.96,"callDelta":0.13,"callVolume":15,"callIv":50.49,"callOi":102,"putOption":"2027-01-15_67.50_Put","putPrice":27.15,"putDelta":-0.87,"putVolume":0,"putIv":47.54,"putOi":396},{"callOption":"2027-01-15_70.00_Call","callPrice":2.6,"callDelta":0.2,"callVolume":0,"callIv":50.87,"callOi":242,"putOption":"2027-01-15_70.00_Put","putPrice":25.55,"putDelta":-0.8,"putVolume":0,"putIv":46.65,"putOi":206},{"callOption":"2027-01-15_72.50_Call","callPrice":1.8,"callDelta":0.18,"callVolume":0,"callIv":60.42,"callOi":84,"putOption":"2027-01-15_72.50_Put","putPrice":27.0,"putDelta":-0.82,"putVolume":0,"putIv":47.66,"putOi":60},{"callOption":"2027-01-15_75.00_Call","callPrice":0.45,"callDelta":0.16,"callVolume":0,"callIv":64.93,"callOi":139,"putOption":"2027-01-15_75.00_Put","putPrice":27.92,"putDelta":-0.84,"putVolume":0,"putIv":0.0,"putOi":262},{"callOption":"2027-01-15_77.50_Call","callPrice":1.55,"callDelta":0.15,"callVolume":0,"callIv":55.06,"callOi":98,"putOption":"2027-01-15_77.50_Put","putPrice":35.9,"putDelta":-0.85,"putVolume":0,"putIv":0.0,"putOi":3},{"callOption":"2027-01-15_80.00_Call","callPrice":1.8,"callDelta":0.13,"callVolume":0,"callIv":57.03,"callOi":74,"putOption":"2027-01-15_80.00_Put","putPrice":36.29,"putDelta":-0.87,"putVolume":0,"putIv":0.0,"putOi":2},{"callOption":"2027-01-15_82.50_Call","callPrice":2.25,"callDelta":0.12,"callVolume":0,"callIv":54.09,"callOi":20,"putOption":"2027-01-15_82.50_Put","putPrice":7.4,"putDelta":-0.88,"putVolume":0,"putIv":0.0,"putOi":1},{"callOption":"2027-01-15_85.00_Call","callPrice":0.5,"callDelta":0.05,"callVolume":1,"callIv":53.59,"callOi":425,"putOption":"2027-01-15_85.00_Put","putPrice":34.0,"putDelta":0.0,"putVolume":0,"putIv":0.0,"putOi":0},{"callOption":"2027-01-15_90.00_Call","callPrice":0.65,"callDelta":0.09,"callVolume":0,"callIv":75.34,"callOi":45,"putOption":"2027-01-15_90.00_Put","putPrice":48.8,"putDelta":0.0,"putVolume":0,"putIv":0.0,"putOi":0},{"callOption":"2027-01-15_95.00_Call","callPrice":0.4,"callDelta":0.07,"callVolume":0,"callIv":74.53,"callOi":377,"putOption":"2027-01-15_95.00_Put","putPrice":53.8,"putDelta":0.0,"putVolume":0,"putIv":0.0,"putOi":0},{"callOption":"2027-01-15_100.00_Call","callPrice":0.5,"callDelta":0.06,"callVolume":0,"callIv":72.66,"callOi":421,"putOption":"2027-01-15_100.00_Put","putPrice":58.8,"putDelta":0.0,"putVolume":0,"putIv":0.0,"putOi":0},{"callOption":"2027-01-15_40.00_Call","callPrice":6.1,"callDelta":0.6,"callVolume":1,"callIv":52.59,"callOi":121,"putOption":"2027-01-15_40.00_Put","putPrice":5.35,"putDelta":-0.39,"putVolume":4,"putIv":51.48,"putOi":63},{"callOption":"2027-01-15_42.50_Call","callPrice":4.1,"callDelta":0.58,"callVolume":0,"callIv":52.07,"callOi":36,"putOption":"2027-01-15_42.50_Put","putPrice":7.9,"putDelta":-0.42,"putVolume":0,"putIv":49.62,"putOi":62},{"callOption":"2027-01-15_45.00_Call","callPrice":4.7,"callDelta":0.48,"callVolume":2,"callIv":51.61,"callOi":58,"putOption":"2027-01-15_45.00_Put","putPrice":8.4,"putDelta":-0.52,"putVolume":1,"putIv":49.04,"putOi":68},{"callOption":"2027-01-15_47.50_Call","callPrice":3.06,"callDelta":0.49,"callVolume":0,"callIv":51.3,"callOi":56,"putOption":"2027-01-15_47.50_Put","putPrice":11.2,"putDelta":-0.51,"putVolume":0,"putIv":51.54,"putOi":2127},{"callOption":"2027-01-15_105.00_Call","callPrice":0.3,"callDelta":0.05,"callVolume":0,"callIv":80.14,"callOi":89,"putOption":"2027-01-15_105.00_Put","putPrice":63.8,"putDelta":0.0,"putVolume":0,"putIv":0.0,"putOi":0},{"callOption":"2027-01-15_110.00_Call","callPrice":0.6,"callDelta":0.04,"callVolume":0,"callIv":86.6,"callOi":6,"putOption":"2027-01-15_110.00_Put","putPrice":68.8,"putDelta":0.0,"putVolume":0,"putIv":0.0,"putOi":0},{"callOption":"2027-01-15_115.00_Call","callPrice":0.75,"callDelta":0.03,"callVolume":0,"callIv":89.27,"callOi":8,"putOption":"2027-01-15_115.00_Put","putPrice":73.8,"putDelta":0.0,"putVolume":0,"putIv":0.0,"putOi":0},{"callOption":"2027-01-15_37.50_Call","callPrice":8.1,"callDelta":0.66,"callVolume":2,"callIv":50.33,"callOi":12,"putOption":"2027-01-15_37.50_Put","putPrice":4.33,"putDelta":-0.33,"putVolume":2,"putIv":52.95,"putOi":2151},{"callOption":"2027-01-15_87.50_Call","callPrice":0.33,"callDelta":0.04,"callVolume":1,"callIv":52.59,"callOi":220,"putOption":"2027-01-15_87.50_Put","putPrice":9.8,"putDelta":-0.96,"putVolume":0,"putIv":0.0,"putOi":1},{"callOption":"2027-01-15_120.00_Call","callPrice":1.1,"callDelta":0.02,"callVolume":0,"callIv":91.79,"callOi":124,"putOption":"2027-01-15_120.00_Put","putPrice":78.8,"putDelta":0.0,"putVolume":0,"putIv":0.0,"putOi":0},{"callOption":"2027-01-15_22.50_Call","callPrice":19.35,"callDelta":0.92,"callVolume":0,"callIv":70.17,"callOi":0,"putOption":"2027-01-15_22.50_Put","putPrice":0.65,"putDelta":-0.08,"putVolume":0,"putIv":83.11,"putOi":7},{"callOption":"2027-01-15_92.50_Call","callPrice":1.18,"callDelta":0.08,"callVolume":0,"callIv":77.1,"callOi":1,"putOption":"2027-01-15_92.50_Put","putPrice":51.3,"putDelta":0.0,"putVolume":0,"putIv":0.0,"putOi":0},{"callOption":"2027-01-15_97.50_Call","callPrice":2.7,"callDelta":0.06,"callVolume":0,"callIv":77.03,"callOi":53,"putOption":"2027-01-15_97.50_Put","putPrice":56.3,"putDelta":0.0,"putVolume":0,"putIv":0.0,"putOi":0},{"callOption":"2027-01-15_125.00_Call","callPrice":1.1,"callDelta":0.02,"callVolume":0,"callIv":94.18,"callOi":10,"putOption":"2027-01-15_125.00_Put","putPrice":83.8,"putDelta":0.0,"putVolume":0,"putIv":0.0,"putOi":0},{"callOption":"2027-01-15_130.00_Call","callPrice":0.05,"callDelta":0.02,"callVolume":0,"callIv":96.45,"callOi":26,"putOption":"2027-01-15_130.00_Put","putPrice":88.8,"putDelta":0.0,"putVolume":0,"putIv":0.0,"putOi":0},{"callOption":"2027-01-15_35.00_Call","callPrice":7.62,"callDelta":0.73,"callVolume":0,"callIv":50.98,"callOi":38,"putOption":"2027-01-15_35.00_Put","putPrice":3.92,"putDelta":-0.27,"putVolume":0,"putIv":53.47,"putOi":275},{"callOption":"2027-01-15_62.50_Call","callPrice":1.0,"callDelta":0.27,"callVolume":0,"callIv":49.62,"callOi":74,"putOption":"2027-01-15_62.50_Put","putPrice":23.05,"putDelta":-0.84,"putVolume":24,"putIv":49.73,"putOi":185},{"callOption":"2027-01-15_25.00_Call","callPrice":17.15,"callDelta":0.89,"callVolume":0,"callIv":65.77,"callOi":0,"putOption":"2027-01-15_25.00_Put","putPrice":0.9,"putDelta":-0.11,"putVolume":0,"putIv":59.63,"putOi":5},{"callOption":"2027-01-15_27.50_Call","callPrice":14.55,"callDelta":0.88,"callVolume":0,"callIv":53.95,"callOi":0,"putOption":"2027-01-15_27.50_Put","putPrice":1.37,"putDelta":-0.12,"putVolume":20,"putIv":57.3,"putOi":298},{"callOption":"2027-01-15_30.00_Call","callPrice":14.0,"callDelta":0.83,"callVolume":0,"callIv":53.65,"callOi":5,"putOption":"2027-01-15_30.00_Put","putPrice":1.95,"putDelta":-0.16,"putVolume":17,"putIv":56.05,"putOi":61},{"callOption":"2027-01-15_57.50_Call","callPrice":1.3,"callDelta":0.33,"callVolume":0,"callIv":50.33,"callOi":41,"putOption":"2027-01-15_57.50_Put","putPrice":10.75,"putDelta":-0.67,"putVolume":0,"putIv":49.29,"putOi":8},{"callOption":"2027-01-15_52.50_Call","callPrice":2.85,"callDelta":0.3,"callVolume":1,"callIv":48.42,"callOi":12,"putOption":"2027-01-15_52.50_Put","putPrice":8.35,"putDelta":-0.7,"putVolume":0,"putIv":50.65,"putOi":67},{"callOption":"2027-01-15_32.50_Call","callPrice":10.85,"callDelta":0.78,"callVolume":0,"callIv":52.58,"callOi":0,"putOption":"2027-01-15_32.50_Put","putPrice":2.45,"putDelta":-0.21,"putVolume":47,"putIv":54.71,"putOi":122},{"callOption":"2027-03-19_22.50_Call","callPrice":19.35,"callDelta":0.91,"callVolume":0,"callIv":62.12,"callOi":0,"putOption":"2027-03-19_22.50_Put","putPrice":0.93,"putDelta":-0.08,"putVolume":0,"putIv":61.78,"putOi":0},{"callOption":"2027-03-19_25.00_Call","callPrice":16.85,"callDelta":0.9,"callVolume":5,"callIv":53.71,"callOi":3,"putOption":"2027-03-19_25.00_Put","putPrice":1.32,"putDelta":-0.1,"putVolume":0,"putIv":57.44,"putOi":1},{"callOption":"2027-03-19_27.50_Call","callPrice":14.85,"callDelta":0.86,"callVolume":5,"callIv":53.39,"callOi":0,"putOption":"2027-03-19_27.50_Put","putPrice":1.8,"putDelta":-0.13,"putVolume":1,"putIv":55.09,"putOi":34},{"callOption":"2027-03-19_30.00_Call","callPrice":12.42,"callDelta":0.81,"callVolume":0,"callIv":53.03,"callOi":2,"putOption":"2027-03-19_30.00_Put","putPrice":2.5,"putDelta":-0.17,"putVolume":1,"putIv":52.62,"putOi":15},{"callOption":"2027-03-19_95.00_Call","callPrice":1.18,"callDelta":0.12,"callVolume":0,"callIv":68.83,"callOi":0,"putOption":"2027-03-19_95.00_Put","putPrice":42.3,"putDelta":0.0,"putVolume":0,"putIv":0.0,"putOi":0},{"callOption":"2027-03-19_72.50_Call","callPrice":1.46,"callDelta":0.24,"callVolume":0,"callIv":56.09,"callOi":8,"putOption":"2027-03-19_72.50_Put","putPrice":31.55,"putDelta":-0.94,"putVolume":0,"putIv":43.21,"putOi":0},{"callOption":"2027-03-19_90.00_Call","callPrice":1.2,"callDelta":0.13,"callVolume":0,"callIv":66.15,"callOi":0,"putOption":"2027-03-19_90.00_Put","putPrice":48.8,"putDelta":0.0,"putVolume":0,"putIv":0.0,"putOi":0},{"callOption":"2027-03-19_85.00_Call","callPrice":0.6,"callDelta":0.16,"callVolume":0,"callIv":54.9,"callOi":3,"putOption":"2027-03-19_85.00_Put","putPrice":43.8,"putDelta":0.0,"putVolume":0,"putIv":0.0,"putOi":0},{"callOption":"2027-03-19_80.00_Call","callPrice":1.77,"callDelta":0.18,"callVolume":0,"callIv":60.3,"callOi":6,"putOption":"2027-03-19_80.00_Put","putPrice":18.88,"putDelta":0.0,"putVolume":0,"putIv":0.0,"putOi":0},{"callOption":"2027-03-19_75.00_Call","callPrice":2.1,"callDelta":0.22,"callVolume":0,"callIv":59.66,"callOi":2,"putOption":"2027-03-19_75.00_Put","putPrice":33.95,"putDelta":-0.98,"putVolume":0,"putIv":41.44,"putOi":0},{"callOption":"2027-03-19_70.00_Call","callPrice":3.87,"callDelta":0.26,"callVolume":0,"callIv":45.91,"callOi":36,"putOption":"2027-03-19_70.00_Put","putPrice":12.18,"putDelta":-0.74,"putVolume":0,"putIv":44.38,"putOi":5},{"callOption":"2027-03-19_67.50_Call","callPrice":3.3,"callDelta":0.18,"callVolume":0,"callIv":51.23,"callOi":0,"putOption":"2027-03-19_67.50_Put","putPrice":17.06,"putDelta":-0.82,"putVolume":0,"putIv":44.54,"putOi":50},{"callOption":"2027-03-19_65.00_Call","callPrice":1.55,"callDelta":0.3,"callVolume":0,"callIv":47.91,"callOi":2,"putOption":"2027-03-19_65.00_Put","putPrice":9.81,"putDelta":-0.7,"putVolume":0,"putIv":46.76,"putOi":6},{"callOption":"2027-03-19_62.50_Call","callPrice":2.0,"callDelta":0.33,"callVolume":0,"callIv":46.64,"callOi":50,"putOption":"2027-03-19_62.50_Put","putPrice":14.57,"putDelta":-0.67,"putVolume":0,"putIv":45.63,"putOi":1},{"callOption":"2027-03-19_60.00_Call","callPrice":1.5,"callDelta":0.35,"callVolume":0,"callIv":49.68,"callOi":9,"putOption":"2027-03-19_60.00_Put","putPrice":21.25,"putDelta":-0.65,"putVolume":0,"putIv":47.3,"putOi":18},{"callOption":"2027-03-19_57.50_Call","callPrice":2.13,"callDelta":0.38,"callVolume":0,"callIv":47.85,"callOi":5,"putOption":"2027-03-19_57.50_Put","putPrice":10.3,"putDelta":-0.62,"putVolume":0,"putIv":47.63,"putOi":5},{"callOption":"2027-03-19_55.00_Call","callPrice":2.05,"callDelta":0.42,"callVolume":0,"callIv":48.84,"callOi":19,"putOption":"2027-03-19_55.00_Put","putPrice":15.3,"putDelta":-0.58,"putVolume":0,"putIv":44.31,"putOi":140},{"callOption":"2027-03-19_52.50_Call","callPrice":3.2,"callDelta":0.35,"callVolume":1,"callIv":49.94,"callOi":96,"putOption":"2027-03-19_52.50_Put","putPrice":15.69,"putDelta":-0.65,"putVolume":0,"putIv":49.29,"putOi":61},{"callOption":"2027-03-19_50.00_Call","callPrice":4.1,"callDelta":0.39,"callVolume":1,"callIv":49.02,"callOi":18,"putOption":"2027-03-19_50.00_Put","putPrice":13.52,"putDelta":-0.61,"putVolume":0,"putIv":49.62,"putOi":1022},{"callOption":"2027-03-19_47.50_Call","callPrice":4.93,"callDelta":0.45,"callVolume":20,"callIv":50.78,"callOi":21,"putOption":"2027-03-19_47.50_Put","putPrice":11.0,"putDelta":-0.55,"putVolume":0,"putIv":46.98,"putOi":237},{"callOption":"2027-03-19_45.00_Call","callPrice":5.8,"callDelta":0.5,"callVolume":2,"callIv":51.36,"callOi":23,"putOption":"2027-03-19_45.00_Put","putPrice":9.2,"putDelta":-0.5,"putVolume":0,"putIv":48.02,"putOi":31},{"callOption":"2027-03-19_42.50_Call","callPrice":6.69,"callDelta":0.6,"callVolume":0,"callIv":51.09,"callOi":1,"putOption":"2027-03-19_42.50_Put","putPrice":7.83,"putDelta":-0.4,"putVolume":0,"putIv":50.35,"putOi":41},{"callOption":"2027-03-19_40.00_Call","callPrice":6.5,"callDelta":0.64,"callVolume":0,"callIv":52.51,"callOi":14,"putOption":"2027-03-19_40.00_Put","putPrice":6.7,"putDelta":-0.36,"putVolume":0,"putIv":49.85,"putOi":215},{"callOption":"2027-03-19_37.50_Call","callPrice":18.0,"callDelta":0.69,"callVolume":0,"callIv":54.16,"callOi":1,"putOption":"2027-03-19_37.50_Put","putPrice":5.5,"putDelta":-0.31,"putVolume":0,"putIv":50.96,"putOi":19},{"callOption":"2027-03-19_35.00_Call","callPrice":13.5,"callDelta":0.73,"callVolume":0,"callIv":54.35,"callOi":3,"putOption":"2027-03-19_35.00_Put","putPrice":4.5,"putDelta":-0.27,"putVolume":0,"putIv":51.34,"putOi":11},{"callOption":"2027-03-19_32.50_Call","callPrice":15.31,"callDelta":0.77,"callVolume":0,"callIv":52.61,"callOi":2,"putOption":"2027-03-19_32.50_Put","putPrice":3.5,"putDelta":-0.23,"putVolume":0,"putIv":53.91,"putOi":12},{"callOption":"2027-06-17_22.50_Call","callPrice":19.75,"callDelta":0.89,"callVolume":0,"callIv":61.14,"callOi":0,"putOption":"2027-06-17_22.50_Put","putPrice":1.3,"putDelta":-0.09,"putVolume":0,"putIv":59.63,"putOi":0},{"callOption":"2027-06-17_65.00_Call","callPrice":2.0,"callDelta":0.22,"callVolume":0,"callIv":47.39,"callOi":0,"putOption":"2027-06-17_65.00_Put","putPrice":25.1,"putDelta":-0.79,"putVolume":0,"putIv":45.62,"putOi":0},{"callOption":"2027-06-17_60.00_Call","callPrice":2.4,"callDelta":0.41,"callVolume":0,"callIv":48.44,"callOi":7,"putOption":"2027-06-17_60.00_Put","putPrice":21.09,"putDelta":-0.59,"putVolume":0,"putIv":46.37,"putOi":1},{"callOption":"2027-06-17_55.00_Call","callPrice":3.34,"callDelta":0.46,"callVolume":0,"callIv":53.15,"callOi":5,"putOption":"2027-06-17_55.00_Put","putPrice":16.8,"putDelta":-0.65,"putVolume":0,"putIv":46.71,"putOi":0},{"callOption":"2027-06-17_52.50_Call","callPrice":4.25,"callDelta":0.39,"callVolume":0,"callIv":49.13,"callOi":0,"putOption":"2027-06-17_52.50_Put","putPrice":14.9,"putDelta":-0.61,"putVolume":0,"putIv":47.0,"putOi":0},{"callOption":"2027-06-17_50.00_Call","callPrice":4.6,"callDelta":0.43,"callVolume":7,"callIv":49.8,"callOi":1,"putOption":"2027-06-17_50.00_Put","putPrice":13.5,"putDelta":-0.55,"putVolume":0,"putIv":50.0,"putOi":0},{"callOption":"2027-06-17_47.50_Call","callPrice":5.18,"callDelta":0.56,"callVolume":0,"callIv":49.94,"callOi":5,"putOption":"2027-06-17_47.50_Put","putPrice":11.9,"putDelta":-0.51,"putVolume":0,"putIv":51.06,"putOi":0},{"callOption":"2027-06-17_45.00_Call","callPrice":4.9,"callDelta":0.59,"callVolume":0,"callIv":50.77,"callOi":2,"putOption":"2027-06-17_45.00_Put","putPrice":9.89,"putDelta":-0.41,"putVolume":0,"putIv":52.16,"putOi":1},{"callOption":"2027-06-17_42.50_Call","callPrice":7.5,"callDelta":0.56,"callVolume":0,"callIv":51.29,"callOi":0,"putOption":"2027-06-17_42.50_Put","putPrice":8.0,"putDelta":-0.44,"putVolume":0,"putIv":53.94,"putOi":15},{"callOption":"2027-06-17_40.00_Call","callPrice":8.3,"callDelta":0.66,"callVolume":0,"callIv":49.43,"callOi":9,"putOption":"2027-06-17_40.00_Put","putPrice":6.9,"putDelta":-0.37,"putVolume":1,"putIv":48.73,"putOi":1},{"callOption":"2027-06-17_37.50_Call","callPrice":9.39,"callDelta":0.66,"callVolume":7,"callIv":54.28,"callOi":8,"putOption":"2027-06-17_37.50_Put","putPrice":5.65,"putDelta":-0.32,"putVolume":0,"putIv":49.58,"putOi":0},{"callOption":"2027-06-17_35.00_Call","callPrice":10.85,"callDelta":0.7,"callVolume":0,"callIv":51.65,"callOi":0,"putOption":"2027-06-17_35.00_Put","putPrice":4.55,"putDelta":-0.27,"putVolume":0,"putIv":50.28,"putOi":0},{"callOption":"2027-06-17_32.50_Call","callPrice":9.9,"callDelta":0.77,"callVolume":0,"callIv":52.38,"callOi":4,"putOption":"2027-06-17_32.50_Put","putPrice":3.9,"putDelta":-0.23,"putVolume":0,"putIv":57.78,"putOi":2},{"callOption":"2027-06-17_30.00_Call","callPrice":14.25,"callDelta":0.79,"callVolume":2,"callIv":56.56,"callOi":0,"putOption":"2027-06-17_30.00_Put","putPrice":2.8,"putDelta":-0.19,"putVolume":68,"putIv":52.83,"putOi":0},{"callOption":"2027-06-17_27.50_Call","callPrice":15.9,"callDelta":0.82,"callVolume":2,"callIv":62.44,"callOi":0,"putOption":"2027-06-17_27.50_Put","putPrice":2.1,"putDelta":-0.15,"putVolume":0,"putIv":53.39,"putOi":0},{"callOption":"2027-06-17_25.00_Call","callPrice":14.63,"callDelta":0.88,"callVolume":0,"callIv":63.13,"callOi":2,"putOption":"2027-06-17_25.00_Put","putPrice":1.75,"putDelta":-0.12,"putVolume":0,"putIv":54.23,"putOi":21},{"callOption":"2028-01-21_22.50_Call","callPrice":20.35,"callDelta":0.87,"callVolume":0,"callIv":56.49,"callOi":0,"putOption":"2028-01-21_22.50_Put","putPrice":1.8,"putDelta":-0.1,"putVolume":0,"putIv":53.15,"putOi":0},{"callOption":"2028-01-21_25.00_Call","callPrice":14.5,"callDelta":0.86,"callVolume":0,"callIv":54.1,"callOi":29,"putOption":"2028-01-21_25.00_Put","putPrice":2.56,"putDelta":-0.14,"putVolume":0,"putIv":47.9,"putOi":24},{"callOption":"2028-01-21_27.50_Call","callPrice":15.0,"callDelta":0.83,"callVolume":0,"callIv":54.46,"callOi":23,"putOption":"2028-01-21_27.50_Put","putPrice":3.6,"putDelta":-0.17,"putVolume":0,"putIv":52.04,"putOi":30},{"callOption":"2028-01-21_30.00_Call","callPrice":14.41,"callDelta":0.81,"callVolume":0,"callIv":55.9,"callOi":19,"putOption":"2028-01-21_30.00_Put","putPrice":5.0,"putDelta":-0.19,"putVolume":0,"putIv":51.91,"putOi":158},{"callOption":"2028-01-21_45.00_Call","callPrice":8.4,"callDelta":0.56,"callVolume":2,"callIv":51.55,"callOi":69,"putOption":"2028-01-21_45.00_Put","putPrice":11.25,"putDelta":-0.44,"putVolume":0,"putIv":49.33,"putOi":226},{"callOption":"2028-01-21_47.50_Call","callPrice":6.0,"callDelta":0.61,"callVolume":0,"callIv":49.74,"callOi":7,"putOption":"2028-01-21_47.50_Put","putPrice":9.7,"putDelta":-0.39,"putVolume":0,"putIv":49.03,"putOi":50},{"callOption":"2028-01-21_50.00_Call","callPrice":7.3,"callDelta":0.48,"callVolume":4,"callIv":49.63,"callOi":144,"putOption":"2028-01-21_50.00_Put","putPrice":15.05,"putDelta":-0.52,"putVolume":0,"putIv":47.08,"putOi":396},{"callOption":"2028-01-21_55.00_Call","callPrice":4.8,"callDelta":0.54,"callVolume":0,"callIv":47.42,"callOi":62,"putOption":"2028-01-21_55.00_Put","putPrice":12.5,"putDelta":-0.46,"putVolume":0,"putIv":45.1,"putOi":45},{"callOption":"2028-01-21_60.00_Call","callPrice":4.53,"callDelta":0.36,"callVolume":1,"callIv":47.4,"callOi":63,"putOption":"2028-01-21_60.00_Put","putPrice":23.08,"putDelta":-0.64,"putVolume":0,"putIv":45.16,"putOi":30},{"callOption":"2028-01-21_62.50_Call","callPrice":3.7,"callDelta":0.48,"callVolume":0,"callIv":47.7,"callOi":187,"putOption":"2028-01-21_62.50_Put","putPrice":16.28,"putDelta":-0.52,"putVolume":0,"putIv":46.0,"putOi":24},{"callOption":"2028-01-21_65.00_Call","callPrice":3.6,"callDelta":0.46,"callVolume":0,"callIv":49.19,"callOi":48,"putOption":"2028-01-21_65.00_Put","putPrice":28.36,"putDelta":-0.54,"putVolume":0,"putIv":44.53,"putOi":23},{"callOption":"2028-01-21_67.50_Call","callPrice":2.8,"callDelta":0.44,"callVolume":0,"callIv":46.95,"callOi":6,"putOption":"2028-01-21_67.50_Put","putPrice":25.95,"putDelta":-0.56,"putVolume":0,"putIv":44.89,"putOi":2},{"callOption":"2028-01-21_70.00_Call","callPrice":2.93,"callDelta":0.27,"callVolume":1,"callIv":47.83,"callOi":81,"putOption":"2028-01-21_70.00_Put","putPrice":15.3,"putDelta":-0.73,"putVolume":0,"putIv":45.33,"putOi":89},{"callOption":"2028-01-21_72.50_Call","callPrice":2.2,"callDelta":0.41,"callVolume":0,"callIv":45.75,"callOi":9,"putOption":"2028-01-21_72.50_Put","putPrice":5.3,"putDelta":-0.59,"putVolume":0,"putIv":44.06,"putOi":12},{"callOption":"2028-01-21_75.00_Call","callPrice":2.69,"callDelta":0.23,"callVolume":2,"callIv":47.29,"callOi":1429,"putOption":"2028-01-21_75.00_Put","putPrice":32.25,"putDelta":-0.77,"putVolume":0,"putIv":45.16,"putOi":43},{"callOption":"2028-01-21_77.50_Call","callPrice":2.2,"callDelta":0.2,"callVolume":3,"callIv":46.05,"callOi":120,"putOption":"2028-01-21_77.50_Put","putPrice":20.5,"putDelta":-0.8,"putVolume":0,"putIv":46.13,"putOi":28},{"callOption":"2028-01-21_80.00_Call","callPrice":1.7,"callDelta":0.36,"callVolume":0,"callIv":46.53,"callOi":44,"putOption":"2028-01-21_80.00_Put","putPrice":35.65,"putDelta":-0.64,"putVolume":0,"putIv":46.1,"putOi":223},{"callOption":"2028-01-21_85.00_Call","callPrice":1.6,"callDelta":0.33,"callVolume":0,"callIv":47.77,"callOi":9,"putOption":"2028-01-21_85.00_Put","putPrice":35.12,"putDelta":-0.67,"putVolume":0,"putIv":42.93,"putOi":70},{"callOption":"2028-01-21_90.00_Call","callPrice":1.4,"callDelta":0.31,"callVolume":0,"callIv":47.89,"callOi":21,"putOption":"2028-01-21_90.00_Put","putPrice":36.98,"putDelta":-0.69,"putVolume":0,"putIv":43.67,"putOi":222},{"callOption":"2028-01-21_95.00_Call","callPrice":1.2,"callDelta":0.29,"callVolume":0,"callIv":48.03,"callOi":18,"putOption":"2028-01-21_95.00_Put","putPrice":44.4,"putDelta":-0.95,"putVolume":0,"putIv":46.42,"putOi":0},{"callOption":"2028-01-21_100.00_Call","callPrice":1.15,"callDelta":0.27,"callVolume":0,"callIv":56.44,"callOi":27,"putOption":"2028-01-21_100.00_Put","putPrice":49.68,"putDelta":-0.95,"putVolume":0,"putIv":49.03,"putOi":0},{"callOption":"2028-01-21_105.00_Call","callPrice":1.7,"callDelta":0.25,"callVolume":0,"callIv":57.57,"callOi":451,"putOption":"2028-01-21_105.00_Put","putPrice":53.82,"putDelta":-0.95,"putVolume":0,"putIv":51.52,"putOi":0},{"callOption":"2028-01-21_35.00_Call","callPrice":11.71,"callDelta":0.7,"callVolume":2,"callIv":51.79,"callOi":15,"putOption":"2028-01-21_35.00_Put","putPrice":6.09,"putDelta":-0.3,"putVolume":0,"putIv":47.16,"putOi":26},{"callOption":"2028-01-21_37.50_Call","callPrice":10.0,"callDelta":0.72,"callVolume":0,"callIv":52.02,"callOi":36,"putOption":"2028-01-21_37.50_Put","putPrice":8.01,"putDelta":-0.28,"putVolume":0,"putIv":49.91,"putOi":57},{"callOption":"2028-01-21_40.00_Call","callPrice":9.5,"callDelta":0.62,"callVolume":20,"callIv":47.63,"callOi":54,"putOption":"2028-01-21_40.00_Put","putPrice":7.95,"putDelta":-0.35,"putVolume":1,"putIv":47.78,"putOi":281},{"callOption":"2028-01-21_42.50_Call","callPrice":10.57,"callDelta":0.67,"callVolume":0,"callIv":50.39,"callOi":20,"putOption":"2028-01-21_42.50_Put","putPrice":8.6,"putDelta":-0.33,"putVolume":0,"putIv":49.47,"putOi":85},{"callOption":"2028-01-21_57.50_Call","callPrice":5.4,"callDelta":0.39,"callVolume":2,"callIv":48.71,"callOi":13,"putOption":"2028-01-21_57.50_Put","putPrice":19.9,"putDelta":-0.61,"putVolume":0,"putIv":45.15,"putOi":36},{"callOption":"2028-01-21_52.50_Call","callPrice":6.4,"callDelta":0.44,"callVolume":1,"callIv":47.92,"callOi":30,"putOption":"2028-01-21_52.50_Put","putPrice":11.35,"putDelta":-0.56,"putVolume":0,"putIv":45.51,"putOi":35},{"callOption":"2028-01-21_32.50_Call","callPrice":14.0,"callDelta":0.78,"callVolume":0,"callIv":49.19,"callOi":39,"putOption":"2028-01-21_32.50_Put","putPrice":5.5,"putDelta":-0.22,"putVolume":0,"putIv":51.34,"putOi":34},{"callOption":"2028-01-21_82.50_Call","callPrice":1.7,"callDelta":0.35,"callVolume":0,"callIv":47.65,"callOi":12,"putOption":"2028-01-21_82.50_Put","putPrice":21.36,"putDelta":-0.65,"putVolume":0,"putIv":46.33,"putOi":103},{"callOption":"2028-01-21_110.00_Call","callPrice":2.1,"callDelta":0.23,"callVolume":0,"callIv":58.96,"callOi":15,"putOption":"2028-01-21_110.00_Put","putPrice":69.0,"putDelta":-0.95,"putVolume":0,"putIv":53.91,"putOi":0},{"callOption":"2028-01-21_87.50_Call","callPrice":1.6,"callDelta":0.32,"callVolume":0,"callIv":48.57,"callOi":45,"putOption":"2028-01-21_87.50_Put","putPrice":46.75,"putDelta":-0.68,"putVolume":0,"putIv":46.52,"putOi":1},{"callOption":"2028-01-21_115.00_Call","callPrice":3.0,"callDelta":0.21,"callVolume":0,"callIv":60.64,"callOi":14,"putOption":"2028-01-21_115.00_Put","putPrice":74.0,"putDelta":-0.95,"putVolume":0,"putIv":56.2,"putOi":0},{"callOption":"2028-01-21_120.00_Call","callPrice":2.35,"callDelta":0.2,"callVolume":0,"callIv":62.64,"callOi":1,"putOption":"2028-01-21_120.00_Put","putPrice":79.0,"putDelta":-0.95,"putVolume":0,"putIv":58.39,"putOi":0},{"callOption":"2028-01-21_92.50_Call","callPrice":1.4,"callDelta":0.3,"callVolume":0,"callIv":57.22,"callOi":2,"putOption":"2028-01-21_92.50_Put","putPrice":51.5,"putDelta":-0.7,"putVolume":0,"putIv":45.06,"putOi":4},{"callOption":"2028-01-21_125.00_Call","callPrice":2.25,"callDelta":0.18,"callVolume":0,"callIv":64.15,"callOi":11,"putOption":"2028-01-21_125.00_Put","putPrice":84.0,"putDelta":-0.94,"putVolume":0,"putIv":60.5,"putOi":0}]}